Workbook

Sheet Dashboard
B2: Customer Churn Dashboard
B3: Telecom subscription customers (IBM Telco sample, 7,043 customers). Use the two filters to explore any segment.
Z4: filter criteria (helper)
B5: Contract filter | C5: All | E5: Internet filter | F5: All | Z5: =IF(C5="All","*",C5) -> *
Z6: =IF(F5="All","*",F5) -> *
B7: =COUNTIFS(Data!$P$2:$P$7044,$Z$5,Data!$I$2:$I$7044,$Z$6) -> 7043 | D7: =IFERROR(COUNTIFS(Data!$P$2:$P$7044,$Z$5,Data!$I$2:$I$7044,$Z$6,Data!$W$2:$W$7044,1)/COUNTIFS(Data!$P$2:$P$7044,$Z$5,Data!$I$2:$I$7044,$Z$6),0) -> 0.26536987 | F7: =SUMIFS(Data!$AA$2:$AA$7044,Data!$P$2:$P$7044,$Z$5,Data!$I$2:$I$7044,$Z$6) -> 139130.85 | H7: =SUMIFS(Data!$AA$2:$AA$7044,Data!$P$2:$P$7044,$Z$5,Data!$I$2:$I$7044,$Z$6)*12 -> 1669570.2 | J7: =IFERROR(AVERAGEIFS(Data!$F$2:$F$7044,Data!$P$2:$P$7044,$Z$5,Data!$I$2:$I$7044,$Z$6,Data!$W$2:$W$7044,1),0) -> 17.979133
B8: Customers | D8: Churn rate | F8: Lost monthly revenue | H8: Annual revenue lost | J8: Avg tenure of churners (months)
B9: =IF(AND(C5="All",F5="All"),"Showing all customers","Showing: "&C5&" contracts, "&F5&" internet") -> Showing all customers
B12: Churn rate by tenure | I12: Churn rate by payment method
B13: Segment | C13: Customers | D13: Churn rate | I13: Segment | J13: Customers | K13: Churn rate
B14: 0-12 months | C14: =COUNTIFS(Data!$P$2:$P$7044,$Z$5,Data!$I$2:$I$7044,$Z$6,Data!$X$2:$X$7044,B14) -> 2186 | D14: =IFERROR(COUNTIFS(Data!$P$2:$P$7044,$Z$5,Data!$I$2:$I$7044,$Z$6,Data!$X$2:$X$7044,B14,Data!$W$2:$W$7044,1)/C14,0) -> 0.47438243 | I14: Electronic check | J14: =COUNTIFS(Data!$P$2:$P$7044,$Z$5,Data!$I$2:$I$7044,$Z$6,Data!$R$2:$R$7044,I14) -> 2365 | K14: =IFERROR(COUNTIFS(Data!$P$2:$P$7044,$Z$5,Data!$I$2:$I$7044,$Z$6,Data!$R$2:$R$7044,I14,Data!$W$2:$W$7044,1)/J14,0) -> 0.45285412
B15: 13-24 months | C15: =COUNTIFS(Data!$P$2:$P$7044,$Z$5,Data!$I$2:$I$7044,$Z$6,Data!$X$2:$X$7044,B15) -> 1024 | D15: =IFERROR(COUNTIFS(Data!$P$2:$P$7044,$Z$5,Data!$I$2:$I$7044,$Z$6,Data!$X$2:$X$7044,B15,Data!$W$2:$W$7044,1)/C15,0) -> 0.28710938 | I15: Mailed check | J15: =COUNTIFS(Data!$P$2:$P$7044,$Z$5,Data!$I$2:$I$7044,$Z$6,Data!$R$2:$R$7044,I15) -> 1612 | K15: =IFERROR(COUNTIFS(Data!$P$2:$P$7044,$Z$5,Data!$I$2:$I$7044,$Z$6,Data!$R$2:$R$7044,I15,Data!$W$2:$W$7044,1)/J15,0) -> 0.191067
B16: 25-48 months | C16: =COUNTIFS(Data!$P$2:$P$7044,$Z$5,Data!$I$2:$I$7044,$Z$6,Data!$X$2:$X$7044,B16) -> 1594 | D16: =IFERROR(COUNTIFS(Data!$P$2:$P$7044,$Z$5,Data!$I$2:$I$7044,$Z$6,Data!$X$2:$X$7044,B16,Data!$W$2:$W$7044,1)/C16,0) -> 0.20388959 | I16: Bank transfer (automatic) | J16: =COUNTIFS(Data!$P$2:$P$7044,$Z$5,Data!$I$2:$I$7044,$Z$6,Data!$R$2:$R$7044,I16) -> 1544 | K16: =IFERROR(COUNTIFS(Data!$P$2:$P$7044,$Z$5,Data!$I$2:$I$7044,$Z$6,Data!$R$2:$R$7044,I16,Data!$W$2:$W$7044,1)/J16,0) -> 0.16709845
B17: 49-72 months | C17: =COUNTIFS(Data!$P$2:$P$7044,$Z$5,Data!$I$2:$I$7044,$Z$6,Data!$X$2:$X$7044,B17) -> 2239 | D17: =IFERROR(COUNTIFS(Data!$P$2:$P$7044,$Z$5,Data!$I$2:$I$7044,$Z$6,Data!$X$2:$X$7044,B17,Data!$W$2:$W$7044,1)/C17,0) -> 0.095131755 | I17: Credit card (automatic) | J17: =COUNTIFS(Data!$P$2:$P$7044,$Z$5,Data!$I$2:$I$7044,$Z$6,Data!$R$2:$R$7044,I17) -> 1522 | K17: =IFERROR(COUNTIFS(Data!$P$2:$P$7044,$Z$5,Data!$I$2:$I$7044,$Z$6,Data!$R$2:$R$7044,I17,Data!$W$2:$W$7044,1)/J17,0) -> 0.15243101
B31: Churn rate by tech support | I31: Churn rate by contract
B32: Segment | C32: Customers | D32: Churn rate | I32: Segment | J32: Customers | K32: Churn rate
B33: No | C33: =COUNTIFS(Data!$P$2:$P$7044,$Z$5,Data!$I$2:$I$7044,$Z$6,Data!$M$2:$M$7044,B33) -> 3473 | D33: =IFERROR(COUNTIFS(Data!$P$2:$P$7044,$Z$5,Data!$I$2:$I$7044,$Z$6,Data!$M$2:$M$7044,B33,Data!$W$2:$W$7044,1)/C33,0) -> 0.41635474 | I33: Month-to-month | J33: =COUNTIFS(Data!$P$2:$P$7044,$Z$5,Data!$I$2:$I$7044,$Z$6,Data!$P$2:$P$7044,I33) -> 3875 | K33: =IFERROR(COUNTIFS(Data!$P$2:$P$7044,$Z$5,Data!$I$2:$I$7044,$Z$6,Data!$P$2:$P$7044,I33,Data!$W$2:$W$7044,1)/J33,0) -> 0.42709677
B34: Yes | C34: =COUNTIFS(Data!$P$2:$P$7044,$Z$5,Data!$I$2:$I$7044,$Z$6,Data!$M$2:$M$7044,B34) -> 2044 | D34: =IFERROR(COUNTIFS(Data!$P$2:$P$7044,$Z$5,Data!$I$2:$I$7044,$Z$6,Data!$M$2:$M$7044,B34,Data!$W$2:$W$7044,1)/C34,0) -> 0.15166341 | I34: One year | J34: =COUNTIFS(Data!$P$2:$P$7044,$Z$5,Data!$I$2:$I$7044,$Z$6,Data!$P$2:$P$7044,I34) -> 1473 | K34: =IFERROR(COUNTIFS(Data!$P$2:$P$7044,$Z$5,Data!$I$2:$I$7044,$Z$6,Data!$P$2:$P$7044,I34,Data!$W$2:$W$7044,1)/J34,0) -> 0.11269518
B35: No internet service | C35: =COUNTIFS(Data!$P$2:$P$7044,$Z$5,Data!$I$2:$I$7044,$Z$6,Data!$M$2:$M$7044,B35) -> 1526 | D35: =IFERROR(COUNTIFS(Data!$P$2:$P$7044,$Z$5,Data!$I$2:$I$7044,$Z$6,Data!$M$2:$M$7044,B35,Data!$W$2:$W$7044,1)/C35,0) -> 0.074049803 | I35: Two year | J35: =COUNTIFS(Data!$P$2:$P$7044,$Z$5,Data!$I$2:$I$7044,$Z$6,Data!$P$2:$P$7044,I35) -> 1695 | K35: =IFERROR(COUNTIFS(Data!$P$2:$P$7044,$Z$5,Data!$I$2:$I$7044,$Z$6,Data!$P$2:$P$7044,I35,Data!$W$2:$W$7044,1)/J35,0) -> 0.028318584
B50: Key findings
B51: 1. Month-to-month customers churn at 42.7%, vs 11.3% on 1-year and 2.8% on 2-year contracts. They make up 87% of lost revenue.
B52: 2. Risk is front-loaded: 47.4% of customers in their first year leave, vs 9.5% after 4+ years.
B53: 3. Electronic-check payers churn at 45.3%, roughly 3x the rate of automatic payers.
B54: 4. Customers without tech support or online security churn at about 42%, vs about 15% with them.
B55: 5. 533 active high-risk customers ($41.8K monthly revenue) are the retention target; see Retention_Scenario.

Sheet README
B2: Customer Churn and Revenue-at-Risk Analysis
B3: Author: Pratiti Toppo | Tools: Excel (formulas, pivots-style analysis, charts, data validation, CHITEST, NORMSINV), SQL
B5: Business question
B6: A subscription telecom company is losing about 1 in 4 customers. Who is leaving, why, how much revenue is at risk, and what should we do?
B8: How to use this workbook
B9: Dashboard: KPIs and charts. Change the yellow filter cells (contract, internet) to explore any segment.
B10: Analysis: churn rate, revenue and lift for 10 customer dimensions.
B11: Stats_Tests: chi-square test for each driver, to check the patterns are not chance.
B12: Risk_Segments: the riskiest combinations of contract, internet and payment method.
B13: At_Risk: a simple 0-6 risk score, proof that it works, and the active customers it flags.
B14: Retention_Scenario: what-if model for a contract-upgrade discount, with a sensitivity table.
B15: Test_Design: sample size for a pilot test of the offer.
... B35: Churn = customers who left within the last month of the snapshot.

Sheet Data
A1: customerID | B1: gender | C1: SeniorCitizen | D1: Partner | E1: Dependents | F1: tenure | G1: PhoneService | H1: MultipleLines | I1: InternetService | J1: OnlineSecurity | K1: OnlineBackup | L1: DeviceProtection | M1: TechSupport | N1: StreamingTV | O1: StreamingMovies | P1: Contract | Q1: PaperlessBilling | R1: PaymentMethod | S1: MonthlyCharges | T1: TotalCharges | U1: Churn | V1: TotalCharges_Clean | W1: Churn_Flag | X1: Tenure_Band | Y1: Senior | Z1: Addon_Count | AA1: Lost_MRR | AB1: Risk_Score | AC1: Risk_Level
A2: 7590-VHVEG | B2: Female | C2: 0 | D2: Yes | E2: No | F2: 1 | G2: No | H2: No phone service | I2: DSL | J2: No | K2: Yes | L2: No | M2: No | N2: No | O2: No | P2: Month-to-month | Q2: Yes | R2: Electronic check | S2: 29.85 | T2: 29.85 | U2: No | V2: =IF(ISNUMBER(T2),T2,0) -> 29.85 | W2: =IF(U2="Yes",1,0) -> 0 | X2: =IF(F2<=12,"0-12 months",IF(F2<=24,"13-24 months",IF(F2<=48,"25-48 months","49-72 months"))) -> 0-12 months | Y2: =IF(C2=1,"Yes","No") -> No | Z2: =COUNTIF(J2:O2,"Yes") -> 1 | AA2: =S2*W2 -> 0 | AB2: =(P2="Month-to-month")+(I2="Fiber optic")+(R2="Electronic check")+(F2<=12)+(M2="No")+(J2="No") -> 5 | AC2: =IF(AB2>=5,"High",IF(AB2>=3,"Medium","Low")) -> High
A3: 5575-GNVDE | B3: Male | C3: 0 | D3: No | E3: No | F3: 34 | G3: Yes | H3: No | I3: DSL | J3: Yes | K3: No | L3: Yes | M3: No | N3: No | O3: No | P3: One year | Q3: No | R3: Mailed check | S3: 56.95 | T3: 1889.5 | U3: No | V3: =IF(ISNUMBER(T3),T3,0) -> 1889.5 | W3: =IF(U3="Yes",1,0) -> 0 | X3: =IF(F3<=12,"0-12 months",IF(F3<=24,"13-24 months",IF(F3<=48,"25-48 months","49-72 months"))) -> 25-48 months | Y3: =IF(C3=1,"Yes","No") -> No | Z3: =COUNTIF(J3:O3,"Yes") -> 2 | AA3: =S3*W3 -> 0 | AB3: =(P3="Month-to-month")+(I3="Fiber optic")+(R3="Electronic check")+(F3<=12)+(M3="No")+(J3="No") -> 1 | AC3: =IF(AB3>=5,"High",IF(AB3>=3,"Medium","Low")) -> Low
A4: 3668-QPYBK | B4: Male | C4: 0 | D4: No | E4: No | F4: 2 | G4: Yes | H4: No | I4: DSL | J4: Yes | K4: Yes | L4: No | M4: No | N4: No | O4: No | P4: Month-to-month | Q4: Yes | R4: Mailed check | S4: 53.85 | T4: 108.15 | U4: Yes | V4: =IF(ISNUMBER(T4),T4,0) -> 108.15 | W4: =IF(U4="Yes",1,0) -> 1 | X4: =IF(F4<=12,"0-12 months",IF(F4<=24,"13-24 months",IF(F4<=48,"25-48 months","49-72 months"))) -> 0-12 months | Y4: =IF(C4=1,"Yes","No") -> No | Z4: =COUNTIF(J4:O4,"Yes") -> 2 | AA4: =S4*W4 -> 53.85 | AB4: =(P4="Month-to-month")+(I4="Fiber optic")+(R4="Electronic check")+(F4<=12)+(M4="No")+(J4="No") -> 3 | AC4: =IF(AB4>=5,"High",IF(AB4>=3,"Medium","Low")) -> Medium
A5: 7795-CFOCW | B5: Male | C5: 0 | D5: No | E5: No | F5: 45 | G5: No | H5: No phone service | I5: DSL | J5: Yes | K5: No | L5: Yes | M5: Yes | N5: No | O5: No | P5: One year | Q5: No | R5: Bank transfer (automatic) | S5: 42.3 | T5: 1840.75 | U5: No | V5: =IF(ISNUMBER(T5),T5,0) -> 1840.75 | W5: =IF(U5="Yes",1,0) -> 0 | X5: =IF(F5<=12,"0-12 months",IF(F5<=24,"13-24 months",IF(F5<=48,"25-48 months","49-72 months"))) -> 25-48 months | Y5: =IF(C5=1,"Yes","No") -> No | Z5: =COUNTIF(J5:O5,"Yes") -> 3 | AA5: =S5*W5 -> 0 | AB5: =(P5="Month-to-month")+(I5="Fiber optic")+(R5="Electronic check")+(F5<=12)+(M5="No")+(J5="No") -> 0 | AC5: =IF(AB5>=5,"High",IF(AB5>=3,"Medium","Low")) -> Low
A6: 9237-HQITU | B6: Female | C6: 0 | D6: No | E6: No | F6: 2 | G6: Yes | H6: No | I6: Fiber optic | J6: No | K6: No | L6: No | M6: No | N6: No | O6: No | P6: Month-to-month | Q6: Yes | R6: Electronic check | S6: 70.7 | T6: 151.65 | U6: Yes | V6: =IF(ISNUMBER(T6),T6,0) -> 151.65 | W6: =IF(U6="Yes",1,0) -> 1 | X6: =IF(F6<=12,"0-12 months",IF(F6<=24,"13-24 months",IF(F6<=48,"25-48 months","49-72 months"))) -> 0-12 months | Y6: =IF(C6=1,"Yes","No") -> No | Z6: =COUNTIF(J6:O6,"Yes") -> 0 | AA6: =S6*W6 -> 70.7 | AB6: =(P6="Month-to-month")+(I6="Fiber optic")+(R6="Electronic check")+(F6<=12)+(M6="No")+(J6="No") -> 6 | AC6: =IF(AB6>=5,"High",IF(AB6>=3,"Medium","Low")) -> High
A7: 9305-CDSKC | B7: Female | C7: 0 | D7: No | E7: No | F7: 8 | G7: Yes | H7: Yes | I7: Fiber optic | J7: No | K7: No | L7: Yes | M7: No | N7: Yes | O7: Yes | P7: Month-to-month | Q7: Yes | R7: Electronic check | S7: 99.65 | T7: 820.5 | U7: Yes | V7: =IF(ISNUMBER(T7),T7,0) -> 820.5 | W7: =IF(U7="Yes",1,0) -> 1 | X7: =IF(F7<=12,"0-12 months",IF(F7<=24,"13-24 months",IF(F7<=48,"25-48 months","49-72 months"))) -> 0-12 months | Y7: =IF(C7=1,"Yes","No") -> No | Z7: =COUNTIF(J7:O7,"Yes") -> 3 | AA7: =S7*W7 -> 99.65 | AB7: =(P7="Month-to-month")+(I7="Fiber optic")+(R7="Electronic check")+(F7<=12)+(M7="No")+(J7="No") -> 6 | AC7: =IF(AB7>=5,"High",IF(AB7>=3,"Medium","Low")) -> High
A8: 1452-KIOVK | B8: Male | C8: 0 | D8: No | E8: Yes | F8: 22 | G8: Yes | H8: Yes | I8: Fiber optic | J8: No | K8: Yes | L8: No | M8: No | N8: Yes | O8: No | P8: Month-to-month | Q8: Yes | R8: Credit card (automatic) | S8: 89.1 | T8: 1949.4 | U8: No | V8: =IF(ISNUMBER(T8),T8,0) -> 1949.4 | W8: =IF(U8="Yes",1,0) -> 0 | X8: =IF(F8<=12,"0-12 months",IF(F8<=24,"13-24 months",IF(F8<=48,"25-48 months","49-72 months"))) -> 13-24 months | Y8: =IF(C8=1,"Yes","No") -> No | Z8: =COUNTIF(J8:O8,"Yes") -> 2 | AA8: =S8*W8 -> 0 | AB8: =(P8="Month-to-month")+(I8="Fiber optic")+(R8="Electronic check")+(F8<=12)+(M8="No")+(J8="No") -> 4 | AC8: =IF(AB8>=5,"High",IF(AB8>=3,"Medium","Low")) -> Medium
A9: 6713-OKOMC | B9: Female | C9: 0 | D9: No | E9: No | F9: 10 | G9: No | H9: No phone service | I9: DSL | J9: Yes | K9: No | L9: No | M9: No | N9: No | O9: No | P9: Month-to-month | Q9: No | R9: Mailed check | S9: 29.75 | T9: 301.9 | U9: No | V9: =IF(ISNUMBER(T9),T9,0) -> 301.9 | W9: =IF(U9="Yes",1,0) -> 0 | X9: =IF(F9<=12,"0-12 months",IF(F9<=24,"13-24 months",IF(F9<=48,"25-48 months","49-72 months"))) -> 0-12 months | Y9: =IF(C9=1,"Yes","No") -> No | Z9: =COUNTIF(J9:O9,"Yes") -> 1 | AA9: =S9*W9 -> 0 | AB9: =(P9="Month-to-month")+(I9="Fiber optic")+(R9="Electronic check")+(F9<=12)+(M9="No")+(J9="No") -> 3 | AC9: =IF(AB9>=5,"High",IF(AB9>=3,"Medium","Low")) -> Medium
A10: 7892-POOKP | B10: Female | C10: 0 | D10: Yes | E10: No | F10: 28 | G10: Yes | H10: Yes | I10: Fiber optic | J10: No | K10: No | L10: Yes | M10: Yes | N10: Yes | O10: Yes | P10: Month-to-month | Q10: Yes | R10: Electronic check | S10: 104.8 | T10: 3046.05 | U10: Yes | V10: =IF(ISNUMBER(T10),T10,0) -> 3046.05 | W10: =IF(U10="Yes",1,0) -> 1 | X10: =IF(F10<=12,"0-12 months",IF(F10<=24,"13-24 months",IF(F10<=48,"25-48 months","49-72 months"))) -> 25-48 months | Y10: =IF(C10=1,"Yes","No") -> No | Z10: =COUNTIF(J10:O10,"Yes") -> 4 | AA10: =S10*W10 -> 104.8 | AB10: =(P10="Month-to-month")+(I10="Fiber optic")+(R10="Electronic check")+(F10<=12)+(M10="No")+(J10="No") -> 4 | AC10: =IF(AB10>=5,"High",IF(AB10>=3,"Medium","Low")) -> Medium
A11: 6388-TABGU | B11: Male | C11: 0 | D11: No | E11: Yes | F11: 62 | G11: Yes | H11: No | I11: DSL | J11: Yes | K11: Yes | L11: No | M11: No | N11: No | O11: No | P11: One year | Q11: No | R11: Bank transfer (automatic) | S11: 56.15 | T11: 3487.95 | U11: No | V11: =IF(ISNUMBER(T11),T11,0) -> 3487.95 | W11: =IF(U11="Yes",1,0) -> 0 | X11: =IF(F11<=12,"0-12 months",IF(F11<=24,"13-24 months",IF(F11<=48,"25-48 months","49-72 months"))) -> 49-72 months | Y11: =IF(C11=1,"Yes","No") -> No | Z11: =COUNTIF(J11:O11,"Yes") -> 2 | AA11: =S11*W11 -> 0 | AB11: =(P11="Month-to-month")+(I11="Fiber optic")+(R11="Electronic check")+(F11<=12)+(M11="No")+(J11="No") -> 1 | AC11: =IF(AB11>=5,"High",IF(AB11>=3,"Medium","Low")) -> Low
A12: 9763-GRSKD | B12: Male | C12: 0 | D12: Yes | E12: Yes | F12: 13 | G12: Yes | H12: No | I12: DSL | J12: Yes | K12: No | L12: No | M12: No | N12: No | O12: No | P12: Month-to-month | Q12: Yes | R12: Mailed check | S12: 49.95 | T12: 587.45 | U12: No | V12: =IF(ISNUMBER(T12),T12,0) -> 587.45 | W12: =IF(U12="Yes",1,0) -> 0 | X12: =IF(F12<=12,"0-12 months",IF(F12<=24,"13-24 months",IF(F12<=48,"25-48 months","49-72 months"))) -> 13-24 months | Y12: =IF(C12=1,"Yes","No") -> No | Z12: =COUNTIF(J12:O12,"Yes") -> 1 | AA12: =S12*W12 -> 0 | AB12: =(P12="Month-to-month")+(I12="Fiber optic")+(R12="Electronic check")+(F12<=12)+(M12="No")+(J12="No") -> 2 | AC12: =IF(AB12>=5,"High",IF(AB12>=3,"Medium","Low")) -> Low
A13: 7469-LKBCI | B13: Male | C13: 0 | D13: No | E13: No | F13: 16 | G13: Yes | H13: No | I13: No | J13: No internet service | K13: No internet service | L13: No internet service | M13: No internet service | N13: No internet service | O13: No internet service | P13: Two year | Q13: No | R13: Credit card (automatic) | S13: 18.95 | T13: 326.8 | U13: No | V13: =IF(ISNUMBER(T13),T13,0) -> 326.8 | W13: =IF(U13="Yes",1,0) -> 0 | X13: =IF(F13<=12,"0-12 months",IF(F13<=24,"13-24 months",IF(F13<=48,"25-48 months","49-72 months"))) -> 13-24 months | Y13: =IF(C13=1,"Yes","No") -> No | Z13: =COUNTIF(J13:O13,"Yes") -> 0 | AA13: =S13*W13 -> 0 | AB13: =(P13="Month-to-month")+(I13="Fiber optic")+(R13="Electronic check")+(F13<=12)+(M13="No")+(J13="No") -> 0 | AC13: =IF(AB13>=5,"High",IF(AB13>=3,"Medium","Low")) -> Low
... A489: 3649-JPUGY | B489: Male | C489: 0 | D489: No | E489: No | F489: 72 | G489: Yes | H489: Yes | I489: DSL | J489: No | K489: Yes | L489: Yes | M489: Yes | N489: Yes | O489: Yes | P489: Two year | Q489: Yes | R489: Bank transfer (automatic) | S489: 88.6 | T489: 6201.95 | U489: No | V489: =IF(ISNUMBER(T489),T489,0) -> 6201.95 | W489: =IF(U489="Yes",1,0) -> 0 | X489: =IF(F489<=12,"0-12 months",IF(F489<=24,"13-24 months",IF(F489<=48,"25-48 months","49-72 months"))) -> 49-72 months | Y489: =IF(C489=1,"Yes","No") -> No | Z489: =COUNTIF(J489:O489,"Yes") -> 5 | AA489: =S489*W489 -> 0 | AB489: =(P489="Month-to-month")+(I489="Fiber optic")+(R489="Electronic check")+(F489<=12)+(M489="No")+(J489="No") -> 1 | AC489: =IF(AB489>=5,"High",IF(AB489>=3,"Medium","Low")) -> Low
A490: 4472-LVYGI | B490: Female | C490: 0 | D490: Yes | E490: Yes | F490: 0 | G490: No | H490: No phone service | I490: DSL | J490: Yes | K490: No | L490: Yes | M490: Yes | N490: Yes | O490: No | P490: Two year | Q490: Yes | R490: Bank transfer (automatic) | S490: 52.55 | U490: No | V490: =IF(ISNUMBER(T490),T490,0) -> 0 | W490: =IF(U490="Yes",1,0) -> 0 | X490: =IF(F490<=12,"0-12 months",IF(F490<=24,"13-24 months",IF(F490<=48,"25-48 months","49-72 months"))) -> 0-12 months | Y490: =IF(C490=1,"Yes","No") -> No | Z490: =COUNTIF(J490:O490,"Yes") -> 4 | AA490: =S490*W490 -> 0 | AB490: =(P490="Month-to-month")+(I490="Fiber optic")+(R490="Electronic check")+(F490<=12)+(M490="No")+(J490="No") -> 1 | AC490: =IF(AB490>=5,"High",IF(AB490>=3,"Medium","Low")) -> Low
A491: 8372-JUXUI | B491: Male | C491: 0 | D491: No | E491: Yes | F491: 1 | G491: Yes | H491: Yes | I491: Fiber optic | J491: No | K491: No | L491: No | M491: No | N491: No | O491: No | P491: Month-to-month | Q491: Yes | R491: Electronic check | S491: 74.35 | T491: 74.35 | U491: Yes | V491: =IF(ISNUMBER(T491),T491,0) -> 74.35 | W491: =IF(U491="Yes",1,0) -> 1 | X491: =IF(F491<=12,"0-12 months",IF(F491<=24,"13-24 months",IF(F491<=48,"25-48 months","49-72 months"))) -> 0-12 months | Y491: =IF(C491=1,"Yes","No") -> No | Z491: =COUNTIF(J491:O491,"Yes") -> 0 | AA491: =S491*W491 -> 74.35 | AB491: =(P491="Month-to-month")+(I491="Fiber optic")+(R491="Electronic check")+(F491<=12)+(M491="No")+(J491="No") -> 6 | AC491: =IF(AB491>=5,"High",IF(AB491>=3,"Medium","Low")) -> High
A492: 3552-CTCYF | B492: Male | C492: 0 | D492: Yes | E492: Yes | F492: 63 | G492: Yes | H492: Yes | I492: Fiber optic | J492: No | K492: Yes | L492: Yes | M492: No | N492: Yes | O492: Yes | P492: Two year | Q492: Yes | R492: Bank transfer (automatic) | S492: 104.8 | T492: 6597.25 | U492: No | V492: =IF(ISNUMBER(T492),T492,0) -> 6597.25 | W492: =IF(U492="Yes",1,0) -> 0 | X492: =IF(F492<=12,"0-12 months",IF(F492<=24,"13-24 months",IF(F492<=48,"25-48 months","49-72 months"))) -> 49-72 months | Y492: =IF(C492=1,"Yes","No") -> No | Z492: =COUNTIF(J492:O492,"Yes") -> 4 | AA492: =S492*W492 -> 0 | AB492: =(P492="Month-to-month")+(I492="Fiber optic")+(R492="Electronic check")+(F492<=12)+(M492="No")+(J492="No") -> 3 | AC492: =IF(AB492>=5,"High",IF(AB492>=3,"Medium","Low")) -> Medium
A493: 6778-YSNIH | B493: Female | C493: 0 | D493: No | E493: No | F493: 2 | G493: Yes | H493: No | I493: DSL | J493: No | K493: Yes | L493: No | M493: No | N493: Yes | O493: No | P493: Month-to-month | Q493: Yes | R493: Electronic check | S493: 59 | T493: 114.15 | U493: No | V493: =IF(ISNUMBER(T493),T493,0) -> 114.15 | W493: =IF(U493="Yes",1,0) -> 0 | X493: =IF(F493<=12,"0-12 months",IF(F493<=24,"13-24 months",IF(F493<=48,"25-48 months","49-72 months"))) -> 0-12 months | Y493: =IF(C493=1,"Yes","No") -> No | Z493: =COUNTIF(J493:O493,"Yes") -> 2 | AA493: =S493*W493 -> 0 | AB493: =(P493="Month-to-month")+(I493="Fiber optic")+(R493="Electronic check")+(F493<=12)+(M493="No")+(J493="No") -> 5 | AC493: =IF(AB493>=5,"High",IF(AB493>=3,"Medium","Low")) -> High
A494: 0388-EOPEX | B494: Female | C494: 0 | D494: Yes | E494: No | F494: 2 | G494: Yes | H494: No | I494: Fiber optic | J494: Yes | K494: No | L494: No | M494: No | N494: No | O494: No | P494: Month-to-month | Q494: Yes | R494: Electronic check | S494: 74.4 | T494: 139.4 | U494: Yes | V494: =IF(ISNUMBER(T494),T494,0) -> 139.4 | W494: =IF(U494="Yes",1,0) -> 1 | X494: =IF(F494<=12,"0-12 months",IF(F494<=24,"13-24 months",IF(F494<=48,"25-48 months","49-72 months"))) -> 0-12 months | Y494: =IF(C494=1,"Yes","No") -> No | Z494: =COUNTIF(J494:O494,"Yes") -> 1 | AA494: =S494*W494 -> 74.4 | AB494: =(P494="Month-to-month")+(I494="Fiber optic")+(R494="Electronic check")+(F494<=12)+(M494="No")+(J494="No") -> 5 | AC494: =IF(AB494>=5,"High",IF(AB494>=3,"Medium","Low")) -> High
A495: 5756-OZRIO | B495: Male | C495: 1 | D495: Yes | E495: No | F495: 61 | G495: Yes | H495: Yes | I495: DSL | J495: No | K495: Yes | L495: No | M495: No | N495: No | O495: Yes | P495: One year | Q495: No | R495: Bank transfer (automatic) | S495: 64.05 | T495: 3902.6 | U495: No | V495: =IF(ISNUMBER(T495),T495,0) -> 3902.6 | W495: =IF(U495="Yes",1,0) -> 0 | X495: =IF(F495<=12,"0-12 months",IF(F495<=24,"13-24 months",IF(F495<=48,"25-48 months","49-72 months"))) -> 49-72 months | Y495: =IF(C495=1,"Yes","No") -> Yes | Z495: =COUNTIF(J495:O495,"Yes") -> 2 | AA495: =S495*W495 -> 0 | AB495: =(P495="Month-to-month")+(I495="Fiber optic")+(R495="Electronic check")+(F495<=12)+(M495="No")+(J495="No") -> 2 | AC495: =IF(AB495>=5,"High",IF(AB495>=3,"Medium","Low")) -> Low
A496: 6579-JPICP | B496: Male | C496: 0 | D496: No | E496: No | F496: 1 | G496: Yes | H496: No | I496: No | J496: No internet service | K496: No internet service | L496: No internet service | M496: No internet service | N496: No internet service | O496: No internet service | P496: Month-to-month | Q496: No | R496: Mailed check | S496: 20.4 | T496: 20.4 | U496: No | V496: =IF(ISNUMBER(T496),T496,0) -> 20.4 | W496: =IF(U496="Yes",1,0) -> 0 | X496: =IF(F496<=12,"0-12 months",IF(F496<=24,"13-24 months",IF(F496<=48,"25-48 months","49-72 months"))) -> 0-12 months | Y496: =IF(C496=1,"Yes","No") -> No | Z496: =COUNTIF(J496:O496,"Yes") -> 0 | AA496: =S496*W496 -> 0 | AB496: =(P496="Month-to-month")+(I496="Fiber optic")+(R496="Electronic check")+(F496<=12)+(M496="No")+(J496="No") -> 2 | AC496: =IF(AB496>=5,"High",IF(AB496>=3,"Medium","Low")) -> Low
A497: 8205-OTCHB | B497: Male | C497: 0 | D497: No | E497: No | F497: 22 | G497: No | H497: No phone service | I497: DSL | J497: No | K497: Yes | L497: Yes | M497: No | N497: No | O497: Yes | P497: One year | Q497: Yes | R497: Bank transfer (automatic) | S497: 43.75 | T497: 903.6 | U497: Yes | V497: =IF(ISNUMBER(T497),T497,0) -> 903.6 | W497: =IF(U497="Yes",1,0) -> 1 | X497: =IF(F497<=12,"0-12 months",IF(F497<=24,"13-24 months",IF(F497<=48,"25-48 months","49-72 months"))) -> 13-24 months | Y497: =IF(C497=1,"Yes","No") -> No | Z497: =COUNTIF(J497:O497,"Yes") -> 3 | AA497: =S497*W497 -> 43.75 | AB497: =(P497="Month-to-month")+(I497="Fiber optic")+(R497="Electronic check")+(F497<=12)+(M497="No")+(J497="No") -> 2 | AC497: =IF(AB497>=5,"High",IF(AB497>=3,"Medium","Low")) -> Low
A498: 4134-BSXLX | B498: Male | C498: 0 | D498: Yes | E498: No | F498: 28 | G498: Yes | H498: No | I498: DSL | J498: Yes | K498: Yes | L498: No | M498: Yes | N498: No | O498: No | P498: Month-to-month | Q498: No | R498: Mailed check | S498: 60.9 | T498: 1785.65 | U498: No | V498: =IF(ISNUMBER(T498),T498,0) -> 1785.65 | W498: =IF(U498="Yes",1,0) -> 0 | X498: =IF(F498<=12,"0-12 months",IF(F498<=24,"13-24 months",IF(F498<=48,"25-48 months","49-72 months"))) -> 25-48 months | Y498: =IF(C498=1,"Yes","No") -> No | Z498: =COUNTIF(J498:O498,"Yes") -> 3 | AA498: =S498*W498 -> 0 | AB498: =(P498="Month-to-month")+(I498="Fiber optic")+(R498="Electronic check")+(F498<=12)+(M498="No")+(J498="No") -> 1 | AC498: =IF(AB498>=5,"High",IF(AB498>=3,"Medium","Low")) -> Low
A499: 0505-SPOOW | B499: Female | C499: 0 | D499: Yes | E499: No | F499: 70 | G499: Yes | H499: No | I499: No | J499: No internet service | K499: No internet service | L499: No internet service | M499: No internet service | N499: No internet service | O499: No internet service | P499: Two year | Q499: No | R499: Bank transfer (automatic) | S499: 19.8 | T499: 1397.65 | U499: No | V499: =IF(ISNUMBER(T499),T499,0) -> 1397.65 | W499: =IF(U499="Yes",1,0) -> 0 | X499: =IF(F499<=12,"0-12 months",IF(F499<=24,"13-24 months",IF(F499<=48,"25-48 months","49-72 months"))) -> 49-72 months | Y499: =IF(C499=1,"Yes","No") -> No | Z499: =COUNTIF(J499:O499,"Yes") -> 0 | AA499: =S499*W499 -> 0 | AB499: =(P499="Month-to-month")+(I499="Fiber optic")+(R499="Electronic check")+(F499<=12)+(M499="No")+(J499="No") -> 0 | AC499: =IF(AB499>=5,"High",IF(AB499>=3,"Medium","Low")) -> Low
A500: 6235-VDHOM | B500: Female | C500: 1 | D500: No | E500: No | F500: 5 | G500: No | H500: No phone service | I500: DSL | J500: No | K500: Yes | L500: No | M500: No | N500: No | O500: No | P500: Month-to-month | Q500: No | R500: Electronic check | S500: 28.45 | T500: 131.05 | U500: Yes | V500: =IF(ISNUMBER(T500),T500,0) -> 131.05 | W500: =IF(U500="Yes",1,0) -> 1 | X500: =IF(F500<=12,"0-12 months",IF(F500<=24,"13-24 months",IF(F500<=48,"25-48 months","49-72 months"))) -> 0-12 months | Y500: =IF(C500=1,"Yes","No") -> Yes | Z500: =COUNTIF(J500:O500,"Yes") -> 1 | AA500: =S500*W500 -> 28.45 | AB500: =(P500="Month-to-month")+(I500="Fiber optic")+(R500="Electronic check")+(F500<=12)+(M500="No")+(J500="No") -> 5 | AC500: =IF(AB500>=5,"High",IF(AB500>=3,"Medium","Low")) -> High
A501: 7783-YKGDV | B501: Female | C501: 0 | D501: No | E501: No | F501: 12 | G501: Yes | H501: Yes | I501: Fiber optic | J501: Yes | K501: Yes | L501: Yes | M501: No | N501: No | O501: Yes | P501: Month-to-month | Q501: Yes | R501: Bank transfer (automatic) | S501: 99.7 | T501: 1238.45 | U501: Yes | V501: =IF(ISNUMBER(T501),T501,0) -> 1238.45 | W501: =IF(U501="Yes",1,0) -> 1 | X501: =IF(F501<=12,"0-12 months",IF(F501<=24,"13-24 months",IF(F501<=48,"25-48 months","49-72 months"))) -> 0-12 months | Y501: =IF(C501=1,"Yes","No") -> No | Z501: =COUNTIF(J501:O501,"Yes") -> 4 | AA501: =S501*W501 -> 99.7 | AB501: =(P501="Month-to-month")+(I501="Fiber optic")+(R501="Electronic check")+(F501<=12)+(M501="No")+(J501="No") -> 4 | AC501: =IF(AB501>=5,"High",IF(AB501>=3,"Medium","Low")) -> Medium
A502: 4374-YMUSQ | B502: Male | C502: 0 | D502: No | E502: No | F502: 34 | G502: Yes | H502: Yes | I502: Fiber optic | J502: Yes | K502: Yes | L502: Yes | M502: Yes | N502: Yes | O502: Yes | P502: One year | Q502: No | R502: Credit card (automatic) | S502: 116.25 | T502: 3899.05 | U502: No | V502: =IF(ISNUMBER(T502),T502,0) -> 3899.05 | W502: =IF(U502="Yes",1,0) -> 0 | X502: =IF(F502<=12,"0-12 months",IF(F502<=24,"13-24 months",IF(F502<=48,"25-48 months","49-72 months"))) -> 25-48 months | Y502: =IF(C502=1,"Yes","No") -> No | Z502: =COUNTIF(J502:O502,"Yes") -> 6 | AA502: =S502*W502 -> 0 | AB502: =(P502="Month-to-month")+(I502="Fiber optic")+(R502="Electronic check")+(F502<=12)+(M502="No")+(J502="No") -> 1 | AC502: =IF(AB502>=5,"High",IF(AB502>=3,"Medium","Low")) -> Low
... A754: 1410-RSCMR | B754: Male | C754: 0 | D754: Yes | E754: Yes | F754: 7 | G754: Yes | H754: No | I754: DSL | J754: Yes | K754: No | L754: Yes | M754: Yes | N754: No | O754: Yes | P754: Month-to-month | Q754: Yes | R754: Credit card (automatic) | S754: 71.35 | T754: 515.75 | U754: No | V754: =IF(ISNUMBER(T754),T754,0) -> 515.75 | W754: =IF(U754="Yes",1,0) -> 0 | X754: =IF(F754<=12,"0-12 months",IF(F754<=24,"13-24 months",IF(F754<=48,"25-48 months","49-72 months"))) -> 0-12 months | Y754: =IF(C754=1,"Yes","No") -> No | Z754: =COUNTIF(J754:O754,"Yes") -> 4 | AA754: =S754*W754 -> 0 | AB754: =(P754="Month-to-month")+(I754="Fiber optic")+(R754="Electronic check")+(F754<=12)+(M754="No")+(J754="No") -> 2 | AC754: =IF(AB754>=5,"High",IF(AB754>=3,"Medium","Low")) -> Low
A755: 3115-CZMZD | B755: Male | C755: 0 | D755: No | E755: Yes | F755: 0 | G755: Yes | H755: No | I755: No | J755: No internet service | K755: No internet service | L755: No internet service | M755: No internet service | N755: No internet service | O755: No internet service | P755: Two year | Q755: No | R755: Mailed check | S755: 20.25 | U755: No | V755: =IF(ISNUMBER(T755),T755,0) -> 0 | W755: =IF(U755="Yes",1,0) -> 0 | X755: =IF(F755<=12,"0-12 months",IF(F755<=24,"13-24 months",IF(F755<=48,"25-48 months","49-72 months"))) -> 0-12 months | Y755: =IF(C755=1,"Yes","No") -> No | Z755: =COUNTIF(J755:O755,"Yes") -> 0 | AA755: =S755*W755 -> 0 | AB755: =(P755="Month-to-month")+(I755="Fiber optic")+(R755="Electronic check")+(F755<=12)+(M755="No")+(J755="No") -> 1 | AC755: =IF(AB755>=5,"High",IF(AB755>=3,"Medium","Low")) -> Low
A756: 0139-IVFJG | B756: Female | C756: 0 | D756: Yes | E756: No | F756: 2 | G756: Yes | H756: No | I756: Fiber optic | J756: Yes | K756: Yes | L756: No | M756: No | N756: Yes | O756: No | P756: Month-to-month | Q756: No | R756: Electronic check | S756: 90.35 | T756: 190.5 | U756: No | V756: =IF(ISNUMBER(T756),T756,0) -> 190.5 | W756: =IF(U756="Yes",1,0) -> 0 | X756: =IF(F756<=12,"0-12 months",IF(F756<=24,"13-24 months",IF(F756<=48,"25-48 months","49-72 months"))) -> 0-12 months | Y756: =IF(C756=1,"Yes","No") -> No | Z756: =COUNTIF(J756:O756,"Yes") -> 3 | AA756: =S756*W756 -> 0 | AB756: =(P756="Month-to-month")+(I756="Fiber optic")+(R756="Electronic check")+(F756<=12)+(M756="No")+(J756="No") -> 5 | AC756: =IF(AB756>=5,"High",IF(AB756>=3,"Medium","Low")) -> High
A757: 6683-VLCTZ | B757: Male | C757: 1 | D757: No | E757: No | F757: 20 | G757: Yes | H757: Yes | I757: Fiber optic | J757: No | K757: No | L757: Yes | M757: No | N757: Yes | O757: Yes | P757: Month-to-month | Q757: Yes | R757: Electronic check | S757: 98.55 | T757: 1842.8 | U757: Yes | V757: =IF(ISNUMBER(T757),T757,0) -> 1842.8 | W757: =IF(U757="Yes",1,0) -> 1 | X757: =IF(F757<=12,"0-12 months",IF(F757<=24,"13-24 months",IF(F757<=48,"25-48 months","49-72 months"))) -> 13-24 months | Y757: =IF(C757=1,"Yes","No") -> Yes | Z757: =COUNTIF(J757:O757,"Yes") -> 3 | AA757: =S757*W757 -> 98.55 | AB757: =(P757="Month-to-month")+(I757="Fiber optic")+(R757="Electronic check")+(F757<=12)+(M757="No")+(J757="No") -> 5 | AC757: =IF(AB757>=5,"High",IF(AB757>=3,"Medium","Low")) -> High
A758: 5730-DBDSI | B758: Male | C758: 0 | D758: No | E758: No | F758: 66 | G758: Yes | H758: No | I758: No | J758: No internet service | K758: No internet service | L758: No internet service | M758: No internet service | N758: No internet service | O758: No internet service | P758: Two year | Q758: No | R758: Bank transfer (automatic) | S758: 19.7 | T758: 1253.8 | U758: No | V758: =IF(ISNUMBER(T758),T758,0) -> 1253.8 | W758: =IF(U758="Yes",1,0) -> 0 | X758: =IF(F758<=12,"0-12 months",IF(F758<=24,"13-24 months",IF(F758<=48,"25-48 months","49-72 months"))) -> 49-72 months | Y758: =IF(C758=1,"Yes","No") -> No | Z758: =COUNTIF(J758:O758,"Yes") -> 0 | AA758: =S758*W758 -> 0 | AB758: =(P758="Month-to-month")+(I758="Fiber optic")+(R758="Electronic check")+(F758<=12)+(M758="No")+(J758="No") -> 0 | AC758: =IF(AB758>=5,"High",IF(AB758>=3,"Medium","Low")) -> Low
A759: 0030-FNXPP | B759: Female | C759: 0 | D759: No | E759: No | F759: 3 | G759: Yes | H759: No | I759: No | J759: No internet service | K759: No internet service | L759: No internet service | M759: No internet service | N759: No internet service | O759: No internet service | P759: Month-to-month | Q759: No | R759: Mailed check | S759: 19.85 | T759: 57.2 | U759: No | V759: =IF(ISNUMBER(T759),T759,0) -> 57.2 | W759: =IF(U759="Yes",1,0) -> 0 | X759: =IF(F759<=12,"0-12 months",IF(F759<=24,"13-24 months",IF(F759<=48,"25-48 months","49-72 months"))) -> 0-12 months | Y759: =IF(C759=1,"Yes","No") -> No | Z759: =COUNTIF(J759:O759,"Yes") -> 0 | AA759: =S759*W759 -> 0 | AB759: =(P759="Month-to-month")+(I759="Fiber optic")+(R759="Electronic check")+(F759<=12)+(M759="No")+(J759="No") -> 2 | AC759: =IF(AB759>=5,"High",IF(AB759>=3,"Medium","Low")) -> Low
A760: 2189-WWOEW | B760: Female | C760: 0 | D760: No | E760: Yes | F760: 15 | G760: Yes | H760: No | I760: Fiber optic | J760: No | K760: Yes | L760: No | M760: No | N760: No | O760: Yes | P760: Month-to-month | Q760: Yes | R760: Bank transfer (automatic) | S760: 85.9 | T760: 1269.55 | U760: Yes | V760: =IF(ISNUMBER(T760),T760,0) -> 1269.55 | W760: =IF(U760="Yes",1,0) -> 1 | X760: =IF(F760<=12,"0-12 months",IF(F760<=24,"13-24 months",IF(F760<=48,"25-48 months","49-72 months"))) -> 13-24 months | Y760: =IF(C760=1,"Yes","No") -> No | Z760: =COUNTIF(J760:O760,"Yes") -> 2 | AA760: =S760*W760 -> 85.9 | AB760: =(P760="Month-to-month")+(I760="Fiber optic")+(R760="Electronic check")+(F760<=12)+(M760="No")+(J760="No") -> 4 | AC760: =IF(AB760>=5,"High",IF(AB760>=3,"Medium","Low")) -> Medium
A761: 5684-FJVYR | B761: Female | C761: 0 | D761: Yes | E761: Yes | F761: 72 | G761: Yes | H761: Yes | I761: Fiber optic | J761: Yes | K761: Yes | L761: No | M761: Yes | N761: No | O761: No | P761: Two year | Q761: Yes | R761: Bank transfer (automatic) | S761: 90.35 | T761: 6563.4 | U761: No | V761: =IF(ISNUMBER(T761),T761,0) -> 6563.4 | W761: =IF(U761="Yes",1,0) -> 0 | X761: =IF(F761<=12,"0-12 months",IF(F761<=24,"13-24 months",IF(F761<=48,"25-48 months","49-72 months"))) -> 49-72 months | Y761: =IF(C761=1,"Yes","No") -> No | Z761: =COUNTIF(J761:O761,"Yes") -> 3 | AA761: =S761*W761 -> 0 | AB761: =(P761="Month-to-month")+(I761="Fiber optic")+(R761="Electronic check")+(F761<=12)+(M761="No")+(J761="No") -> 1 | AC761: =IF(AB761>=5,"High",IF(AB761>=3,"Medium","Low")) -> Low
A762: 4013-GUXND | B762: Male | C762: 0 | D762: No | E762: No | F762: 1 | G762: Yes | H762: No | I762: No | J762: No internet service | K762: No internet service | L762: No internet service | M762: No internet service | N762: No internet service | O762: No internet service | P762: Month-to-month | Q762: No | R762: Mailed check | S762: 20.8 | T762: 20.8 | U762: No | V762: =IF(ISNUMBER(T762),T762,0) -> 20.8 | W762: =IF(U762="Yes",1,0) -> 0 | X762: =IF(F762<=12,"0-12 months",IF(F762<=24,"13-24 months",IF(F762<=48,"25-48 months","49-72 months"))) -> 0-12 months | Y762: =IF(C762=1,"Yes","No") -> No | Z762: =COUNTIF(J762:O762,"Yes") -> 0 | AA762: =S762*W762 -> 0 | AB762: =(P762="Month-to-month")+(I762="Fiber optic")+(R762="Electronic check")+(F762<=12)+(M762="No")+(J762="No") -> 2 | AC762: =IF(AB762>=5,"High",IF(AB762>=3,"Medium","Low")) -> Low
A763: 1894-IGFSG | B763: Female | C763: 0 | D763: No | E763: No | F763: 22 | G763: Yes | H763: No | I763: Fiber optic | J763: No | K763: No | L763: No | M763: No | N763: Yes | O763: Yes | P763: Month-to-month | Q763: No | R763: Electronic check | S763: 89.25 | T763: 1907.85 | U763: Yes | V763: =IF(ISNUMBER(T763),T763,0) -> 1907.85 | W763: =IF(U763="Yes",1,0) -> 1 | X763: =IF(F763<=12,"0-12 months",IF(F763<=24,"13-24 months",IF(F763<=48,"25-48 months","49-72 months"))) -> 13-24 months | Y763: =IF(C763=1,"Yes","No") -> No | Z763: =COUNTIF(J763:O763,"Yes") -> 2 | AA763: =S763*W763 -> 89.25 | AB763: =(P763="Month-to-month")+(I763="Fiber optic")+(R763="Electronic check")+(F763<=12)+(M763="No")+(J763="No") -> 5 | AC763: =IF(AB763>=5,"High",IF(AB763>=3,"Medium","Low")) -> High
A764: 7379-POKDZ | B764: Male | C764: 0 | D764: Yes | E764: No | F764: 3 | G764: Yes | H764: No | I764: Fiber optic | J764: No | K764: No | L764: No | M764: No | N764: No | O764: No | P764: Month-to-month | Q764: Yes | R764: Electronic check | S764: 70.3 | T764: 208.85 | U764: Yes | V764: =IF(ISNUMBER(T764),T764,0) -> 208.85 | W764: =IF(U764="Yes",1,0) -> 1 | X764: =IF(F764<=12,"0-12 months",IF(F764<=24,"13-24 months",IF(F764<=48,"25-48 months","49-72 months"))) -> 0-12 months | Y764: =IF(C764=1,"Yes","No") -> No | Z764: =COUNTIF(J764:O764,"Yes") -> 0 | AA764: =S764*W764 -> 70.3 | AB764: =(P764="Month-to-month")+(I764="Fiber optic")+(R764="Electronic check")+(F764<=12)+(M764="No")+(J764="No") -> 6 | AC764: =IF(AB764>=5,"High",IF(AB764>=3,"Medium","Low")) -> High
A765: 1266-NZYUI | B765: Female | C765: 0 | D765: Yes | E765: Yes | F765: 72 | G765: Yes | H765: Yes | I765: DSL | J765: Yes | K765: No | L765: Yes | M765: Yes | N765: No | O765: No | P765: Two year | Q765: No | R765: Bank transfer (automatic) | S765: 66.85 | T765: 4758.8 | U765: No | V765: =IF(ISNUMBER(T765),T765,0) -> 4758.8 | W765: =IF(U765="Yes",1,0) -> 0 | X765: =IF(F765<=12,"0-12 months",IF(F765<=24,"13-24 months",IF(F765<=48,"25-48 months","49-72 months"))) -> 49-72 months | Y765: =IF(C765=1,"Yes","No") -> No | Z765: =COUNTIF(J765:O765,"Yes") -> 3 | AA765: =S765*W765 -> 0 | AB765: =(P765="Month-to-month")+(I765="Fiber optic")+(R765="Electronic check")+(F765<=12)+(M765="No")+(J765="No") -> 0 | AC765: =IF(AB765>=5,"High",IF(AB765>=3,"Medium","Low")) -> Low
A766: 7969-FFOWG | B766: Male | C766: 0 | D766: Yes | E766: Yes | F766: 65 | G766: Yes | H766: No | I766: No | J766: No internet service | K766: No internet service | L766: No internet service | M766: No internet service | N766: No internet service | O766: No internet service | P766: Two year | Q766: No | R766: Mailed check | S766: 19.9 | T766: 1292.6 | U766: No | V766: =IF(ISNUMBER(T766),T766,0) -> 1292.6 | W766: =IF(U766="Yes",1,0) -> 0 | X766: =IF(F766<=12,"0-12 months",IF(F766<=24,"13-24 months",IF(F766<=48,"25-48 months","49-72 months"))) -> 49-72 months | Y766: =IF(C766=1,"Yes","No") -> No | Z766: =COUNTIF(J766:O766,"Yes") -> 0 | AA766: =S766*W766 -> 0 | AB766: =(P766="Month-to-month")+(I766="Fiber optic")+(R766="Electronic check")+(F766<=12)+(M766="No")+(J766="No") -> 0 | AC766: =IF(AB766>=5,"High",IF(AB766>=3,"Medium","Low")) -> Low
A767: 4718-DHSMV | B767: Female | C767: 0 | D767: No | E767: No | F767: 11 | G767: No | H767: No phone service | I767: DSL | J767: No | K767: No | L767: No | M767: No | N767: Yes | O767: No | P767: Month-to-month | Q767: Yes | R767: Mailed check | S767: 35.8 | T767: 363.15 | U767: No | V767: =IF(ISNUMBER(T767),T767,0) -> 363.15 | W767: =IF(U767="Yes",1,0) -> 0 | X767: =IF(F767<=12,"0-12 months",IF(F767<=24,"13-24 months",IF(F767<=48,"25-48 months","49-72 months"))) -> 0-12 months | Y767: =IF(C767=1,"Yes","No") -> No | Z767: =COUNTIF(J767:O767,"Yes") -> 1 | AA767: =S767*W767 -> 0 | AB767: =(P767="Month-to-month")+(I767="Fiber optic")+(R767="Electronic check")+(F767<=12)+(M767="No")+(J767="No") -> 4 | AC767: =IF(AB767>=5,"High",IF(AB767>=3,"Medium","Low")) -> Medium
... A937: 6630-UJZMY | B937: Female | C937: 1 | D937: Yes | E937: No | F937: 4 | G937: Yes | H937: Yes | I937: Fiber optic | J937: No | K937: No | L937: No | M937: No | N937: Yes | O937: No | P937: Month-to-month | Q937: Yes | R937: Electronic check | S937: 83.25 | T937: 308.05 | U937: No | V937: =IF(ISNUMBER(T937),T937,0) -> 308.05 | W937: =IF(U937="Yes",1,0) -> 0 | X937: =IF(F937<=12,"0-12 months",IF(F937<=24,"13-24 months",IF(F937<=48,"25-48 months","49-72 months"))) -> 0-12 months | Y937: =IF(C937=1,"Yes","No") -> Yes | Z937: =COUNTIF(J937:O937,"Yes") -> 1 | AA937: =S937*W937 -> 0 | AB937: =(P937="Month-to-month")+(I937="Fiber optic")+(R937="Electronic check")+(F937<=12)+(M937="No")+(J937="No") -> 6 | AC937: =IF(AB937>=5,"High",IF(AB937>=3,"Medium","Low")) -> High
A938: 5709-LVOEQ | B938: Female | C938: 0 | D938: Yes | E938: Yes | F938: 0 | G938: Yes | H938: No | I938: DSL | J938: Yes | K938: Yes | L938: Yes | M938: No | N938: Yes | O938: Yes | P938: Two year | Q938: No | R938: Mailed check | S938: 80.85 | U938: No | V938: =IF(ISNUMBER(T938),T938,0) -> 0 | W938: =IF(U938="Yes",1,0) -> 0 | X938: =IF(F938<=12,"0-12 months",IF(F938<=24,"13-24 months",IF(F938<=48,"25-48 months","49-72 months"))) -> 0-12 months | Y938: =IF(C938=1,"Yes","No") -> No | Z938: =COUNTIF(J938:O938,"Yes") -> 5 | AA938: =S938*W938 -> 0 | AB938: =(P938="Month-to-month")+(I938="Fiber optic")+(R938="Electronic check")+(F938<=12)+(M938="No")+(J938="No") -> 2 | AC938: =IF(AB938>=5,"High",IF(AB938>=3,"Medium","Low")) -> Low
A939: 6400-BWQKW | B939: Female | C939: 0 | D939: No | E939: No | F939: 6 | G939: Yes | H939: Yes | I939: Fiber optic | J939: Yes | K939: No | L939: No | M939: No | N939: No | O939: No | P939: Month-to-month | Q939: Yes | R939: Electronic check | S939: 79.05 | T939: 434.5 | U939: Yes | V939: =IF(ISNUMBER(T939),T939,0) -> 434.5 | W939: =IF(U939="Yes",1,0) -> 1 | X939: =IF(F939<=12,"0-12 months",IF(F939<=24,"13-24 months",IF(F939<=48,"25-48 months","49-72 months"))) -> 0-12 months | Y939: =IF(C939=1,"Yes","No") -> No | Z939: =COUNTIF(J939:O939,"Yes") -> 1 | AA939: =S939*W939 -> 79.05 | AB939: =(P939="Month-to-month")+(I939="Fiber optic")+(R939="Electronic check")+(F939<=12)+(M939="No")+(J939="No") -> 5 | AC939: =IF(AB939>=5,"High",IF(AB939>=3,"Medium","Low")) -> High
A940: 2692-AQCPF | B940: Female | C940: 0 | D940: Yes | E940: No | F940: 65 | G940: Yes | H940: Yes | I940: Fiber optic | J940: No | K940: Yes | L940: Yes | M940: Yes | N940: Yes | O940: Yes | P940: One year | Q940: Yes | R940: Credit card (automatic) | S940: 108.05 | T940: 7118.9 | U940: No | V940: =IF(ISNUMBER(T940),T940,0) -> 7118.9 | W940: =IF(U940="Yes",1,0) -> 0 | X940: =IF(F940<=12,"0-12 months",IF(F940<=24,"13-24 months",IF(F940<=48,"25-48 months","49-72 months"))) -> 49-72 months | Y940: =IF(C940=1,"Yes","No") -> No | Z940: =COUNTIF(J940:O940,"Yes") -> 5 | AA940: =S940*W940 -> 0 | AB940: =(P940="Month-to-month")+(I940="Fiber optic")+(R940="Electronic check")+(F940<=12)+(M940="No")+(J940="No") -> 2 | AC940: =IF(AB940>=5,"High",IF(AB940>=3,"Medium","Low")) -> Low
A941: 0347-UBKUZ | B941: Female | C941: 0 | D941: No | E941: No | F941: 15 | G941: Yes | H941: No | I941: No | J941: No internet service | K941: No internet service | L941: No internet service | M941: No internet service | N941: No internet service | O941: No internet service | P941: Month-to-month | Q941: No | R941: Mailed check | S941: 19.9 | T941: 320.45 | U941: No | V941: =IF(ISNUMBER(T941),T941,0) -> 320.45 | W941: =IF(U941="Yes",1,0) -> 0 | X941: =IF(F941<=12,"0-12 months",IF(F941<=24,"13-24 months",IF(F941<=48,"25-48 months","49-72 months"))) -> 13-24 months | Y941: =IF(C941=1,"Yes","No") -> No | Z941: =COUNTIF(J941:O941,"Yes") -> 0 | AA941: =S941*W941 -> 0 | AB941: =(P941="Month-to-month")+(I941="Fiber optic")+(R941="Electronic check")+(F941<=12)+(M941="No")+(J941="No") -> 1 | AC941: =IF(AB941>=5,"High",IF(AB941>=3,"Medium","Low")) -> Low
A942: 0835-DUUIQ | B942: Female | C942: 0 | D942: No | E942: Yes | F942: 24 | G942: Yes | H942: No | I942: No | J942: No internet service | K942: No internet service | L942: No internet service | M942: No internet service | N942: No internet service | O942: No internet service | P942: One year | Q942: No | R942: Bank transfer (automatic) | S942: 21.05 | T942: 531.55 | U942: No | V942: =IF(ISNUMBER(T942),T942,0) -> 531.55 | W942: =IF(U942="Yes",1,0) -> 0 | X942: =IF(F942<=12,"0-12 months",IF(F942<=24,"13-24 months",IF(F942<=48,"25-48 months","49-72 months"))) -> 13-24 months | Y942: =IF(C942=1,"Yes","No") -> No | Z942: =COUNTIF(J942:O942,"Yes") -> 0 | AA942: =S942*W942 -> 0 | AB942: =(P942="Month-to-month")+(I942="Fiber optic")+(R942="Electronic check")+(F942<=12)+(M942="No")+(J942="No") -> 0 | AC942: =IF(AB942>=5,"High",IF(AB942>=3,"Medium","Low")) -> Low
A943: 0811-GSDTP | B943: Female | C943: 0 | D943: No | E943: Yes | F943: 13 | G943: No | H943: No phone service | I943: DSL | J943: No | K943: Yes | L943: No | M943: No | N943: No | O943: No | P943: Month-to-month | Q943: No | R943: Electronic check | S943: 30.15 | T943: 382.2 | U943: No | V943: =IF(ISNUMBER(T943),T943,0) -> 382.2 | W943: =IF(U943="Yes",1,0) -> 0 | X943: =IF(F943<=12,"0-12 months",IF(F943<=24,"13-24 months",IF(F943<=48,"25-48 months","49-72 months"))) -> 13-24 months | Y943: =IF(C943=1,"Yes","No") -> No | Z943: =COUNTIF(J943:O943,"Yes") -> 1 | AA943: =S943*W943 -> 0 | AB943: =(P943="Month-to-month")+(I943="Fiber optic")+(R943="Electronic check")+(F943<=12)+(M943="No")+(J943="No") -> 4 | AC943: =IF(AB943>=5,"High",IF(AB943>=3,"Medium","Low")) -> Medium
A944: 7567-ECMCM | B944: Male | C944: 0 | D944: No | E944: No | F944: 24 | G944: Yes | H944: No | I944: Fiber optic | J944: No | K944: No | L944: No | M944: No | N944: No | O944: Yes | P944: Month-to-month | Q944: Yes | R944: Credit card (automatic) | S944: 79.85 | T944: 2001 | U944: No | V944: =IF(ISNUMBER(T944),T944,0) -> 2001 | W944: =IF(U944="Yes",1,0) -> 0 | X944: =IF(F944<=12,"0-12 months",IF(F944<=24,"13-24 months",IF(F944<=48,"25-48 months","49-72 months"))) -> 13-24 months | Y944: =IF(C944=1,"Yes","No") -> No | Z944: =COUNTIF(J944:O944,"Yes") -> 1 | AA944: =S944*W944 -> 0 | AB944: =(P944="Month-to-month")+(I944="Fiber optic")+(R944="Electronic check")+(F944<=12)+(M944="No")+(J944="No") -> 4 | AC944: =IF(AB944>=5,"High",IF(AB944>=3,"Medium","Low")) -> Medium
A945: 6115-ZTBFQ | B945: Female | C945: 0 | D945: Yes | E945: No | F945: 72 | G945: No | H945: No phone service | I945: DSL | J945: Yes | K945: Yes | L945: Yes | M945: Yes | N945: Yes | O945: Yes | P945: Two year | Q945: No | R945: Bank transfer (automatic) | S945: 65.5 | T945: 4919.7 | U945: No | V945: =IF(ISNUMBER(T945),T945,0) -> 4919.7 | W945: =IF(U945="Yes",1,0) -> 0 | X945: =IF(F945<=12,"0-12 months",IF(F945<=24,"13-24 months",IF(F945<=48,"25-48 months","49-72 months"))) -> 49-72 months | Y945: =IF(C945=1,"Yes","No") -> No | Z945: =COUNTIF(J945:O945,"Yes") -> 6 | AA945: =S945*W945 -> 0 | AB945: =(P945="Month-to-month")+(I945="Fiber optic")+(R945="Electronic check")+(F945<=12)+(M945="No")+(J945="No") -> 0 | AC945: =IF(AB945>=5,"High",IF(AB945>=3,"Medium","Low")) -> Low
A946: 6353-BRMMA | B946: Female | C946: 0 | D946: Yes | E946: Yes | F946: 54 | G946: Yes | H946: Yes | I946: Fiber optic | J946: Yes | K946: Yes | L946: No | M946: No | N946: Yes | O946: Yes | P946: Month-to-month | Q946: Yes | R946: Bank transfer (automatic) | S946: 104.1 | T946: 5645.8 | U946: No | V946: =IF(ISNUMBER(T946),T946,0) -> 5645.8 | W946: =IF(U946="Yes",1,0) -> 0 | X946: =IF(F946<=12,"0-12 months",IF(F946<=24,"13-24 months",IF(F946<=48,"25-48 months","49-72 months"))) -> 49-72 months | Y946: =IF(C946=1,"Yes","No") -> No | Z946: =COUNTIF(J946:O946,"Yes") -> 4 | AA946: =S946*W946 -> 0 | AB946: =(P946="Month-to-month")+(I946="Fiber optic")+(R946="Electronic check")+(F946<=12)+(M946="No")+(J946="No") -> 3 | AC946: =IF(AB946>=5,"High",IF(AB946>=3,"Medium","Low")) -> Medium
A947: 6680-WKXRZ | B947: Female | C947: 0 | D947: No | E947: No | F947: 3 | G947: Yes | H947: Yes | I947: Fiber optic | J947: No | K947: No | L947: No | M947: No | N947: No | O947: No | P947: Month-to-month | Q947: No | R947: Bank transfer (automatic) | S947: 74.4 | T947: 215.8 | U947: Yes | V947: =IF(ISNUMBER(T947),T947,0) -> 215.8 | W947: =IF(U947="Yes",1,0) -> 1 | X947: =IF(F947<=12,"0-12 months",IF(F947<=24,"13-24 months",IF(F947<=48,"25-48 months","49-72 months"))) -> 0-12 months | Y947: =IF(C947=1,"Yes","No") -> No | Z947: =COUNTIF(J947:O947,"Yes") -> 0 | AA947: =S947*W947 -> 74.4 | AB947: =(P947="Month-to-month")+(I947="Fiber optic")+(R947="Electronic check")+(F947<=12)+(M947="No")+(J947="No") -> 5 | AC947: =IF(AB947>=5,"High",IF(AB947>=3,"Medium","Low")) -> High
A948: 6231-WFGFH | B948: Male | C948: 0 | D948: Yes | E948: Yes | F948: 4 | G948: Yes | H948: No | I948: No | J948: No internet service | K948: No internet service | L948: No internet service | M948: No internet service | N948: No internet service | O948: No internet service | P948: Month-to-month | Q948: Yes | R948: Mailed check | S948: 20.5 | T948: 77.6 | U948: No | V948: =IF(ISNUMBER(T948),T948,0) -> 77.6 | W948: =IF(U948="Yes",1,0) -> 0 | X948: =IF(F948<=12,"0-12 months",IF(F948<=24,"13-24 months",IF(F948<=48,"25-48 months","49-72 months"))) -> 0-12 months | Y948: =IF(C948=1,"Yes","No") -> No | Z948: =COUNTIF(J948:O948,"Yes") -> 0 | AA948: =S948*W948 -> 0 | AB948: =(P948="Month-to-month")+(I948="Fiber optic")+(R948="Electronic check")+(F948<=12)+(M948="No")+(J948="No") -> 2 | AC948: =IF(AB948>=5,"High",IF(AB948>=3,"Medium","Low")) -> Low
A949: 9904-EHEVJ | B949: Female | C949: 1 | D949: Yes | E949: Yes | F949: 32 | G949: Yes | H949: Yes | I949: Fiber optic | J949: No | K949: No | L949: Yes | M949: No | N949: Yes | O949: No | P949: Month-to-month | Q949: Yes | R949: Mailed check | S949: 91.35 | T949: 2896.55 | U949: No | V949: =IF(ISNUMBER(T949),T949,0) -> 2896.55 | W949: =IF(U949="Yes",1,0) -> 0 | X949: =IF(F949<=12,"0-12 months",IF(F949<=24,"13-24 months",IF(F949<=48,"25-48 months","49-72 months"))) -> 25-48 months | Y949: =IF(C949=1,"Yes","No") -> Yes | Z949: =COUNTIF(J949:O949,"Yes") -> 2 | AA949: =S949*W949 -> 0 | AB949: =(P949="Month-to-month")+(I949="Fiber optic")+(R949="Electronic check")+(F949<=12)+(M949="No")+(J949="No") -> 4 | AC949: =IF(AB949>=5,"High",IF(AB949>=3,"Medium","Low")) -> Medium
A950: 7028-DVOIQ | B950: Male | C950: 1 | D950: No | E950: No | F950: 35 | G950: Yes | H950: Yes | I950: Fiber optic | J950: No | K950: No | L950: Yes | M950: No | N950: Yes | O950: Yes | P950: Month-to-month | Q950: Yes | R950: Electronic check | S950: 99.05 | T950: 3395.8 | U950: Yes | V950: =IF(ISNUMBER(T950),T950,0) -> 3395.8 | W950: =IF(U950="Yes",1,0) -> 1 | X950: =IF(F950<=12,"0-12 months",IF(F950<=24,"13-24 months",IF(F950<=48,"25-48 months","49-72 months"))) -> 25-48 months | Y950: =IF(C950=1,"Yes","No") -> Yes | Z950: =COUNTIF(J950:O950,"Yes") -> 3 | AA950: =S950*W950 -> 99.05 | AB950: =(P950="Month-to-month")+(I950="Fiber optic")+(R950="Electronic check")+(F950<=12)+(M950="No")+(J950="No") -> 5 | AC950: =IF(AB950>=5,"High",IF(AB950>=3,"Medium","Low")) -> High
... A1083: 1751-NCDLI | B1083: Male | C1083: 1 | D1083: Yes | E1083: No | F1083: 46 | G1083: Yes | H1083: Yes | I1083: Fiber optic | J1083: No | K1083: No | L1083: Yes | M1083: No | N1083: Yes | O1083: Yes | P1083: Month-to-month | Q1083: Yes | R1083: Electronic check | S1083: 98.85 | T1083: 4564.9 | U1083: No | V1083: =IF(ISNUMBER(T1083),T1083,0) -> 4564.9 | W1083: =IF(U1083="Yes",1,0) -> 0 | X1083: =IF(F1083<=12,"0-12 months",IF(F1083<=24,"13-24 months",IF(F1083<=48,"25-48 months","49-72 months"))) -> 25-48 months | Y1083: =IF(C1083=1,"Yes","No") -> Yes | Z1083: =COUNTIF(J1083:O1083,"Yes") -> 3 | AA1083: =S1083*W1083 -> 0 | AB1083: =(P1083="Month-to-month")+(I1083="Fiber optic")+(R1083="Electronic check")+(F1083<=12)+(M1083="No")+(J1083="No") -> 5 | AC1083: =IF(AB1083>=5,"High",IF(AB1083>=3,"Medium","Low")) -> High
A1084: 4367-NUYAO | B1084: Male | C1084: 0 | D1084: Yes | E1084: Yes | F1084: 0 | G1084: Yes | H1084: Yes | I1084: No | J1084: No internet service | K1084: No internet service | L1084: No internet service | M1084: No internet service | N1084: No internet service | O1084: No internet service | P1084: Two year | Q1084: No | R1084: Mailed check | S1084: 25.75 | U1084: No | V1084: =IF(ISNUMBER(T1084),T1084,0) -> 0 | W1084: =IF(U1084="Yes",1,0) -> 0 | X1084: =IF(F1084<=12,"0-12 months",IF(F1084<=24,"13-24 months",IF(F1084<=48,"25-48 months","49-72 months"))) -> 0-12 months | Y1084: =IF(C1084=1,"Yes","No") -> No | Z1084: =COUNTIF(J1084:O1084,"Yes") -> 0 | AA1084: =S1084*W1084 -> 0 | AB1084: =(P1084="Month-to-month")+(I1084="Fiber optic")+(R1084="Electronic check")+(F1084<=12)+(M1084="No")+(J1084="No") -> 1 | AC1084: =IF(AB1084>=5,"High",IF(AB1084>=3,"Medium","Low")) -> Low
A1085: 9878-TNQGW | B1085: Male | C1085: 0 | D1085: No | E1085: No | F1085: 2 | G1085: Yes | H1085: No | I1085: Fiber optic | J1085: No | K1085: No | L1085: No | M1085: No | N1085: No | O1085: Yes | P1085: Month-to-month | Q1085: Yes | R1085: Electronic check | S1085: 80.95 | T1085: 171.15 | U1085: Yes | V1085: =IF(ISNUMBER(T1085),T1085,0) -> 171.15 | W1085: =IF(U1085="Yes",1,0) -> 1 | X1085: =IF(F1085<=12,"0-12 months",IF(F1085<=24,"13-24 months",IF(F1085<=48,"25-48 months","49-72 months"))) -> 0-12 months | Y1085: =IF(C1085=1,"Yes","No") -> No | Z1085: =COUNTIF(J1085:O1085,"Yes") -> 1 | AA1085: =S1085*W1085 -> 80.95 | AB1085: =(P1085="Month-to-month")+(I1085="Fiber optic")+(R1085="Electronic check")+(F1085<=12)+(M1085="No")+(J1085="No") -> 6 | AC1085: =IF(AB1085>=5,"High",IF(AB1085>=3,"Medium","Low")) -> High
A1086: 9170-ARBTB | B1086: Female | C1086: 0 | D1086: Yes | E1086: Yes | F1086: 52 | G1086: Yes | H1086: No | I1086: No | J1086: No internet service | K1086: No internet service | L1086: No internet service | M1086: No internet service | N1086: No internet service | O1086: No internet service | P1086: One year | Q1086: No | R1086: Credit card (automatic) | S1086: 19.6 | T1086: 1012.4 | U1086: No | V1086: =IF(ISNUMBER(T1086),T1086,0) -> 1012.4 | W1086: =IF(U1086="Yes",1,0) -> 0 | X1086: =IF(F1086<=12,"0-12 months",IF(F1086<=24,"13-24 months",IF(F1086<=48,"25-48 months","49-72 months"))) -> 49-72 months | Y1086: =IF(C1086=1,"Yes","No") -> No | Z1086: =COUNTIF(J1086:O1086,"Yes") -> 0 | AA1086: =S1086*W1086 -> 0 | AB1086: =(P1086="Month-to-month")+(I1086="Fiber optic")+(R1086="Electronic check")+(F1086<=12)+(M1086="No")+(J1086="No") -> 0 | AC1086: =IF(AB1086>=5,"High",IF(AB1086>=3,"Medium","Low")) -> Low
A1087: 4441-NIHPT | B1087: Female | C1087: 1 | D1087: No | E1087: No | F1087: 13 | G1087: Yes | H1087: No | I1087: Fiber optic | J1087: No | K1087: No | L1087: Yes | M1087: No | N1087: No | O1087: No | P1087: Month-to-month | Q1087: Yes | R1087: Electronic check | S1087: 74.3 | T1087: 940.35 | U1087: Yes | V1087: =IF(ISNUMBER(T1087),T1087,0) -> 940.35 | W1087: =IF(U1087="Yes",1,0) -> 1 | X1087: =IF(F1087<=12,"0-12 months",IF(F1087<=24,"13-24 months",IF(F1087<=48,"25-48 months","49-72 months"))) -> 13-24 months | Y1087: =IF(C1087=1,"Yes","No") -> Yes | Z1087: =COUNTIF(J1087:O1087,"Yes") -> 1 | AA1087: =S1087*W1087 -> 74.3 | AB1087: =(P1087="Month-to-month")+(I1087="Fiber optic")+(R1087="Electronic check")+(F1087<=12)+(M1087="No")+(J1087="No") -> 5 | AC1087: =IF(AB1087>=5,"High",IF(AB1087>=3,"Medium","Low")) -> High
A1088: 8999-BOHSE | B1088: Female | C1088: 1 | D1088: No | E1088: No | F1088: 11 | G1088: Yes | H1088: No | I1088: Fiber optic | J1088: No | K1088: No | L1088: No | M1088: No | N1088: Yes | O1088: Yes | P1088: Month-to-month | Q1088: No | R1088: Bank transfer (automatic) | S1088: 89.7 | T1088: 1047.7 | U1088: Yes | V1088: =IF(ISNUMBER(T1088),T1088,0) -> 1047.7 | W1088: =IF(U1088="Yes",1,0) -> 1 | X1088: =IF(F1088<=12,"0-12 months",IF(F1088<=24,"13-24 months",IF(F1088<=48,"25-48 months","49-72 months"))) -> 0-12 months | Y1088: =IF(C1088=1,"Yes","No") -> Yes | Z1088: =COUNTIF(J1088:O1088,"Yes") -> 2 | AA1088: =S1088*W1088 -> 89.7 | AB1088: =(P1088="Month-to-month")+(I1088="Fiber optic")+(R1088="Electronic check")+(F1088<=12)+(M1088="No")+(J1088="No") -> 5 | AC1088: =IF(AB1088>=5,"High",IF(AB1088>=3,"Medium","Low")) -> High
A1089: 7241-AJHFS | B1089: Male | C1089: 0 | D1089: No | E1089: No | F1089: 32 | G1089: Yes | H1089: Yes | I1089: Fiber optic | J1089: Yes | K1089: No | L1089: No | M1089: Yes | N1089: No | O1089: No | P1089: Month-to-month | Q1089: No | R1089: Bank transfer (automatic) | S1089: 87.65 | T1089: 2766.4 | U1089: No | V1089: =IF(ISNUMBER(T1089),T1089,0) -> 2766.4 | W1089: =IF(U1089="Yes",1,0) -> 0 | X1089: =IF(F1089<=12,"0-12 months",IF(F1089<=24,"13-24 months",IF(F1089<=48,"25-48 months","49-72 months"))) -> 25-48 months | Y1089: =IF(C1089=1,"Yes","No") -> No | Z1089: =COUNTIF(J1089:O1089,"Yes") -> 2 | AA1089: =S1089*W1089 -> 0 | AB1089: =(P1089="Month-to-month")+(I1089="Fiber optic")+(R1089="Electronic check")+(F1089<=12)+(M1089="No")+(J1089="No") -> 2 | AC1089: =IF(AB1089>=5,"High",IF(AB1089>=3,"Medium","Low")) -> Low
A1090: 7029-RPUAV | B1090: Male | C1090: 1 | D1090: Yes | E1090: No | F1090: 17 | G1090: Yes | H1090: Yes | I1090: Fiber optic | J1090: No | K1090: No | L1090: Yes | M1090: No | N1090: Yes | O1090: Yes | P1090: Month-to-month | Q1090: Yes | R1090: Credit card (automatic) | S1090: 100.45 | T1090: 1622.45 | U1090: Yes | V1090: =IF(ISNUMBER(T1090),T1090,0) -> 1622.45 | W1090: =IF(U1090="Yes",1,0) -> 1 | X1090: =IF(F1090<=12,"0-12 months",IF(F1090<=24,"13-24 months",IF(F1090<=48,"25-48 months","49-72 months"))) -> 13-24 months | Y1090: =IF(C1090=1,"Yes","No") -> Yes | Z1090: =COUNTIF(J1090:O1090,"Yes") -> 3 | AA1090: =S1090*W1090 -> 100.45 | AB1090: =(P1090="Month-to-month")+(I1090="Fiber optic")+(R1090="Electronic check")+(F1090<=12)+(M1090="No")+(J1090="No") -> 4 | AC1090: =IF(AB1090>=5,"High",IF(AB1090>=3,"Medium","Low")) -> Medium
A1091: 4546-FOKWR | B1091: Female | C1091: 0 | D1091: No | E1091: No | F1091: 16 | G1091: Yes | H1091: Yes | I1091: Fiber optic | J1091: No | K1091: No | L1091: No | M1091: No | N1091: No | O1091: No | P1091: Month-to-month | Q1091: Yes | R1091: Credit card (automatic) | S1091: 74.75 | T1091: 1129.35 | U1091: No | V1091: =IF(ISNUMBER(T1091),T1091,0) -> 1129.35 | W1091: =IF(U1091="Yes",1,0) -> 0 | X1091: =IF(F1091<=12,"0-12 months",IF(F1091<=24,"13-24 months",IF(F1091<=48,"25-48 months","49-72 months"))) -> 13-24 months | Y1091: =IF(C1091=1,"Yes","No") -> No | Z1091: =COUNTIF(J1091:O1091,"Yes") -> 0 | AA1091: =S1091*W1091 -> 0 | AB1091: =(P1091="Month-to-month")+(I1091="Fiber optic")+(R1091="Electronic check")+(F1091<=12)+(M1091="No")+(J1091="No") -> 4 | AC1091: =IF(AB1091>=5,"High",IF(AB1091>=3,"Medium","Low")) -> Medium
A1092: 9036-CSKBW | B1092: Female | C1092: 0 | D1092: No | E1092: No | F1092: 51 | G1092: Yes | H1092: Yes | I1092: Fiber optic | J1092: Yes | K1092: Yes | L1092: Yes | M1092: No | N1092: Yes | O1092: Yes | P1092: One year | Q1092: No | R1092: Bank transfer (automatic) | S1092: 107.45 | T1092: 5680.9 | U1092: No | V1092: =IF(ISNUMBER(T1092),T1092,0) -> 5680.9 | W1092: =IF(U1092="Yes",1,0) -> 0 | X1092: =IF(F1092<=12,"0-12 months",IF(F1092<=24,"13-24 months",IF(F1092<=48,"25-48 months","49-72 months"))) -> 49-72 months | Y1092: =IF(C1092=1,"Yes","No") -> No | Z1092: =COUNTIF(J1092:O1092,"Yes") -> 5 | AA1092: =S1092*W1092 -> 0 | AB1092: =(P1092="Month-to-month")+(I1092="Fiber optic")+(R1092="Electronic check")+(F1092<=12)+(M1092="No")+(J1092="No") -> 2 | AC1092: =IF(AB1092>=5,"High",IF(AB1092>=3,"Medium","Low")) -> Low
A1093: 5832-TRLPB | B1093: Male | C1093: 0 | D1093: No | E1093: No | F1093: 29 | G1093: Yes | H1093: No | I1093: DSL | J1093: No | K1093: No | L1093: Yes | M1093: Yes | N1093: Yes | O1093: Yes | P1093: One year | Q1093: Yes | R1093: Bank transfer (automatic) | S1093: 75.35 | T1093: 2243.9 | U1093: No | V1093: =IF(ISNUMBER(T1093),T1093,0) -> 2243.9 | W1093: =IF(U1093="Yes",1,0) -> 0 | X1093: =IF(F1093<=12,"0-12 months",IF(F1093<=24,"13-24 months",IF(F1093<=48,"25-48 months","49-72 months"))) -> 25-48 months | Y1093: =IF(C1093=1,"Yes","No") -> No | Z1093: =COUNTIF(J1093:O1093,"Yes") -> 4 | AA1093: =S1093*W1093 -> 0 | AB1093: =(P1093="Month-to-month")+(I1093="Fiber optic")+(R1093="Electronic check")+(F1093<=12)+(M1093="No")+(J1093="No") -> 1 | AC1093: =IF(AB1093>=5,"High",IF(AB1093>=3,"Medium","Low")) -> Low
A1094: 8590-YFFQO | B1094: Male | C1094: 0 | D1094: Yes | E1094: No | F1094: 70 | G1094: Yes | H1094: No | I1094: DSL | J1094: Yes | K1094: Yes | L1094: Yes | M1094: Yes | N1094: No | O1094: No | P1094: Two year | Q1094: No | R1094: Credit card (automatic) | S1094: 64.95 | T1094: 4523.25 | U1094: No | V1094: =IF(ISNUMBER(T1094),T1094,0) -> 4523.25 | W1094: =IF(U1094="Yes",1,0) -> 0 | X1094: =IF(F1094<=12,"0-12 months",IF(F1094<=24,"13-24 months",IF(F1094<=48,"25-48 months","49-72 months"))) -> 49-72 months | Y1094: =IF(C1094=1,"Yes","No") -> No | Z1094: =COUNTIF(J1094:O1094,"Yes") -> 4 | AA1094: =S1094*W1094 -> 0 | AB1094: =(P1094="Month-to-month")+(I1094="Fiber optic")+(R1094="Electronic check")+(F1094<=12)+(M1094="No")+(J1094="No") -> 0 | AC1094: =IF(AB1094>=5,"High",IF(AB1094>=3,"Medium","Low")) -> Low
A1095: 8659-IOOPU | B1095: Female | C1095: 0 | D1095: Yes | E1095: Yes | F1095: 71 | G1095: Yes | H1095: Yes | I1095: Fiber optic | J1095: Yes | K1095: No | L1095: Yes | M1095: Yes | N1095: No | O1095: Yes | P1095: Two year | Q1095: No | R1095: Electronic check | S1095: 100.45 | T1095: 7159.7 | U1095: No | V1095: =IF(ISNUMBER(T1095),T1095,0) -> 7159.7 | W1095: =IF(U1095="Yes",1,0) -> 0 | X1095: =IF(F1095<=12,"0-12 months",IF(F1095<=24,"13-24 months",IF(F1095<=48,"25-48 months","49-72 months"))) -> 49-72 months | Y1095: =IF(C1095=1,"Yes","No") -> No | Z1095: =COUNTIF(J1095:O1095,"Yes") -> 4 | AA1095: =S1095*W1095 -> 0 | AB1095: =(P1095="Month-to-month")+(I1095="Fiber optic")+(R1095="Electronic check")+(F1095<=12)+(M1095="No")+(J1095="No") -> 2 | AC1095: =IF(AB1095>=5,"High",IF(AB1095>=3,"Medium","Low")) -> Low
A1096: 1338-CECEE | B1096: Male | C1096: 0 | D1096: Yes | E1096: Yes | F1096: 41 | G1096: Yes | H1096: Yes | I1096: DSL | J1096: No | K1096: Yes | L1096: Yes | M1096: No | N1096: Yes | O1096: No | P1096: One year | Q1096: No | R1096: Bank transfer (automatic) | S1096: 68.5 | T1096: 2839.95 | U1096: No | V1096: =IF(ISNUMBER(T1096),T1096,0) -> 2839.95 | W1096: =IF(U1096="Yes",1,0) -> 0 | X1096: =IF(F1096<=12,"0-12 months",IF(F1096<=24,"13-24 months",IF(F1096<=48,"25-48 months","49-72 months"))) -> 25-48 months | Y1096: =IF(C1096=1,"Yes","No") -> No | Z1096: =COUNTIF(J1096:O1096,"Yes") -> 3 | AA1096: =S1096*W1096 -> 0 | AB1096: =(P1096="Month-to-month")+(I1096="Fiber optic")+(R1096="Electronic check")+(F1096<=12)+(M1096="No")+(J1096="No") -> 2 | AC1096: =IF(AB1096>=5,"High",IF(AB1096>=3,"Medium","Low")) -> Low
... A1341: 3838-OZURD | B1341: Male | C1341: 0 | D1341: Yes | E1341: No | F1341: 66 | G1341: Yes | H1341: Yes | I1341: Fiber optic | J1341: No | K1341: Yes | L1341: Yes | M1341: No | N1341: Yes | O1341: Yes | P1341: Month-to-month | Q1341: Yes | R1341: Credit card (automatic) | S1341: 105 | T1341: 7133.25 | U1341: Yes | V1341: =IF(ISNUMBER(T1341),T1341,0) -> 7133.25 | W1341: =IF(U1341="Yes",1,0) -> 1 | X1341: =IF(F1341<=12,"0-12 months",IF(F1341<=24,"13-24 months",IF(F1341<=48,"25-48 months","49-72 months"))) -> 49-72 months | Y1341: =IF(C1341=1,"Yes","No") -> No | Z1341: =COUNTIF(J1341:O1341,"Yes") -> 4 | AA1341: =S1341*W1341 -> 105 | AB1341: =(P1341="Month-to-month")+(I1341="Fiber optic")+(R1341="Electronic check")+(F1341<=12)+(M1341="No")+(J1341="No") -> 4 | AC1341: =IF(AB1341>=5,"High",IF(AB1341>=3,"Medium","Low")) -> Medium
A1342: 1371-DWPAZ | B1342: Female | C1342: 0 | D1342: Yes | E1342: Yes | F1342: 0 | G1342: No | H1342: No phone service | I1342: DSL | J1342: Yes | K1342: Yes | L1342: Yes | M1342: Yes | N1342: Yes | O1342: No | P1342: Two year | Q1342: No | R1342: Credit card (automatic) | S1342: 56.05 | U1342: No | V1342: =IF(ISNUMBER(T1342),T1342,0) -> 0 | W1342: =IF(U1342="Yes",1,0) -> 0 | X1342: =IF(F1342<=12,"0-12 months",IF(F1342<=24,"13-24 months",IF(F1342<=48,"25-48 months","49-72 months"))) -> 0-12 months | Y1342: =IF(C1342=1,"Yes","No") -> No | Z1342: =COUNTIF(J1342:O1342,"Yes") -> 5 | AA1342: =S1342*W1342 -> 0 | AB1342: =(P1342="Month-to-month")+(I1342="Fiber optic")+(R1342="Electronic check")+(F1342<=12)+(M1342="No")+(J1342="No") -> 1 | AC1342: =IF(AB1342>=5,"High",IF(AB1342>=3,"Medium","Low")) -> Low
A1343: 9269-CQOOL | B1343: Male | C1343: 0 | D1343: No | E1343: Yes | F1343: 3 | G1343: Yes | H1343: No | I1343: DSL | J1343: No | K1343: No | L1343: No | M1343: No | N1343: Yes | O1343: No | P1343: Month-to-month | Q1343: Yes | R1343: Credit card (automatic) | S1343: 54.7 | T1343: 169.45 | U1343: Yes | V1343: =IF(ISNUMBER(T1343),T1343,0) -> 169.45 | W1343: =IF(U1343="Yes",1,0) -> 1 | X1343: =IF(F1343<=12,"0-12 months",IF(F1343<=24,"13-24 months",IF(F1343<=48,"25-48 months","49-72 months"))) -> 0-12 months | Y1343: =IF(C1343=1,"Yes","No") -> No | Z1343: =COUNTIF(J1343:O1343,"Yes") -> 1 | AA1343: =S1343*W1343 -> 54.7 | AB1343: =(P1343="Month-to-month")+(I1343="Fiber optic")+(R1343="Electronic check")+(F1343<=12)+(M1343="No")+(J1343="No") -> 4 | AC1343: =IF(AB1343>=5,"High",IF(AB1343>=3,"Medium","Low")) -> Medium
A1344: 2017-CCBLH | B1344: Female | C1344: 0 | D1344: No | E1344: No | F1344: 8 | G1344: Yes | H1344: No | I1344: No | J1344: No internet service | K1344: No internet service | L1344: No internet service | M1344: No internet service | N1344: No internet service | O1344: No internet service | P1344: Two year | Q1344: No | R1344: Mailed check | S1344: 20 | T1344: 141.6 | U1344: No | V1344: =IF(ISNUMBER(T1344),T1344,0) -> 141.6 | W1344: =IF(U1344="Yes",1,0) -> 0 | X1344: =IF(F1344<=12,"0-12 months",IF(F1344<=24,"13-24 months",IF(F1344<=48,"25-48 months","49-72 months"))) -> 0-12 months | Y1344: =IF(C1344=1,"Yes","No") -> No | Z1344: =COUNTIF(J1344:O1344,"Yes") -> 0 | AA1344: =S1344*W1344 -> 0 | AB1344: =(P1344="Month-to-month")+(I1344="Fiber optic")+(R1344="Electronic check")+(F1344<=12)+(M1344="No")+(J1344="No") -> 1 | AC1344: =IF(AB1344>=5,"High",IF(AB1344>=3,"Medium","Low")) -> Low
A1345: 7690-KPNCU | B1345: Male | C1345: 0 | D1345: Yes | E1345: Yes | F1345: 64 | G1345: Yes | H1345: No | I1345: DSL | J1345: Yes | K1345: No | L1345: Yes | M1345: No | N1345: Yes | O1345: Yes | P1345: One year | Q1345: Yes | R1345: Credit card (automatic) | S1345: 73.05 | T1345: 4688.65 | U1345: No | V1345: =IF(ISNUMBER(T1345),T1345,0) -> 4688.65 | W1345: =IF(U1345="Yes",1,0) -> 0 | X1345: =IF(F1345<=12,"0-12 months",IF(F1345<=24,"13-24 months",IF(F1345<=48,"25-48 months","49-72 months"))) -> 49-72 months | Y1345: =IF(C1345=1,"Yes","No") -> No | Z1345: =COUNTIF(J1345:O1345,"Yes") -> 4 | AA1345: =S1345*W1345 -> 0 | AB1345: =(P1345="Month-to-month")+(I1345="Fiber optic")+(R1345="Electronic check")+(F1345<=12)+(M1345="No")+(J1345="No") -> 1 | AC1345: =IF(AB1345>=5,"High",IF(AB1345>=3,"Medium","Low")) -> Low
A1346: 0536-BGFMZ | B1346: Female | C1346: 0 | D1346: Yes | E1346: No | F1346: 28 | G1346: Yes | H1346: No | I1346: No | J1346: No internet service | K1346: No internet service | L1346: No internet service | M1346: No internet service | N1346: No internet service | O1346: No internet service | P1346: Month-to-month | Q1346: No | R1346: Mailed check | S1346: 20.5 | T1346: 563.05 | U1346: No | V1346: =IF(ISNUMBER(T1346),T1346,0) -> 563.05 | W1346: =IF(U1346="Yes",1,0) -> 0 | X1346: =IF(F1346<=12,"0-12 months",IF(F1346<=24,"13-24 months",IF(F1346<=48,"25-48 months","49-72 months"))) -> 25-48 months | Y1346: =IF(C1346=1,"Yes","No") -> No | Z1346: =COUNTIF(J1346:O1346,"Yes") -> 0 | AA1346: =S1346*W1346 -> 0 | AB1346: =(P1346="Month-to-month")+(I1346="Fiber optic")+(R1346="Electronic check")+(F1346<=12)+(M1346="No")+(J1346="No") -> 1 | AC1346: =IF(AB1346>=5,"High",IF(AB1346>=3,"Medium","Low")) -> Low
A1347: 2293-IJWPS | B1347: Female | C1347: 0 | D1347: Yes | E1347: No | F1347: 57 | G1347: Yes | H1347: Yes | I1347: Fiber optic | J1347: No | K1347: No | L1347: Yes | M1347: No | N1347: Yes | O1347: Yes | P1347: One year | Q1347: Yes | R1347: Credit card (automatic) | S1347: 100.75 | T1347: 5985 | U1347: No | V1347: =IF(ISNUMBER(T1347),T1347,0) -> 5985 | W1347: =IF(U1347="Yes",1,0) -> 0 | X1347: =IF(F1347<=12,"0-12 months",IF(F1347<=24,"13-24 months",IF(F1347<=48,"25-48 months","49-72 months"))) -> 49-72 months | Y1347: =IF(C1347=1,"Yes","No") -> No | Z1347: =COUNTIF(J1347:O1347,"Yes") -> 3 | AA1347: =S1347*W1347 -> 0 | AB1347: =(P1347="Month-to-month")+(I1347="Fiber optic")+(R1347="Electronic check")+(F1347<=12)+(M1347="No")+(J1347="No") -> 3 | AC1347: =IF(AB1347>=5,"High",IF(AB1347>=3,"Medium","Low")) -> Medium
A1348: 2845-HSJCY | B1348: Female | C1348: 0 | D1348: Yes | E1348: Yes | F1348: 14 | G1348: Yes | H1348: Yes | I1348: Fiber optic | J1348: No | K1348: No | L1348: Yes | M1348: No | N1348: No | O1348: Yes | P1348: Month-to-month | Q1348: Yes | R1348: Electronic check | S1348: 87.25 | T1348: 1258.6 | U1348: Yes | V1348: =IF(ISNUMBER(T1348),T1348,0) -> 1258.6 | W1348: =IF(U1348="Yes",1,0) -> 1 | X1348: =IF(F1348<=12,"0-12 months",IF(F1348<=24,"13-24 months",IF(F1348<=48,"25-48 months","49-72 months"))) -> 13-24 months | Y1348: =IF(C1348=1,"Yes","No") -> No | Z1348: =COUNTIF(J1348:O1348,"Yes") -> 2 | AA1348: =S1348*W1348 -> 87.25 | AB1348: =(P1348="Month-to-month")+(I1348="Fiber optic")+(R1348="Electronic check")+(F1348<=12)+(M1348="No")+(J1348="No") -> 5 | AC1348: =IF(AB1348>=5,"High",IF(AB1348>=3,"Medium","Low")) -> High
A1349: 5469-NUJUR | B1349: Male | C1349: 0 | D1349: No | E1349: No | F1349: 19 | G1349: Yes | H1349: No | I1349: No | J1349: No internet service | K1349: No internet service | L1349: No internet service | M1349: No internet service | N1349: No internet service | O1349: No internet service | P1349: Two year | Q1349: Yes | R1349: Mailed check | S1349: 19.95 | T1349: 373.5 | U1349: No | V1349: =IF(ISNUMBER(T1349),T1349,0) -> 373.5 | W1349: =IF(U1349="Yes",1,0) -> 0 | X1349: =IF(F1349<=12,"0-12 months",IF(F1349<=24,"13-24 months",IF(F1349<=48,"25-48 months","49-72 months"))) -> 13-24 months | Y1349: =IF(C1349=1,"Yes","No") -> No | Z1349: =COUNTIF(J1349:O1349,"Yes") -> 0 | AA1349: =S1349*W1349 -> 0 | AB1349: =(P1349="Month-to-month")+(I1349="Fiber optic")+(R1349="Electronic check")+(F1349<=12)+(M1349="No")+(J1349="No") -> 0 | AC1349: =IF(AB1349>=5,"High",IF(AB1349>=3,"Medium","Low")) -> Low
A1350: 1184-PJVDB | B1350: Male | C1350: 0 | D1350: Yes | E1350: No | F1350: 10 | G1350: Yes | H1350: No | I1350: Fiber optic | J1350: No | K1350: No | L1350: No | M1350: No | N1350: Yes | O1350: No | P1350: Month-to-month | Q1350: Yes | R1350: Electronic check | S1350: 79.95 | T1350: 857.2 | U1350: Yes | V1350: =IF(ISNUMBER(T1350),T1350,0) -> 857.2 | W1350: =IF(U1350="Yes",1,0) -> 1 | X1350: =IF(F1350<=12,"0-12 months",IF(F1350<=24,"13-24 months",IF(F1350<=48,"25-48 months","49-72 months"))) -> 0-12 months | Y1350: =IF(C1350=1,"Yes","No") -> No | Z1350: =COUNTIF(J1350:O1350,"Yes") -> 1 | AA1350: =S1350*W1350 -> 79.95 | AB1350: =(P1350="Month-to-month")+(I1350="Fiber optic")+(R1350="Electronic check")+(F1350<=12)+(M1350="No")+(J1350="No") -> 6 | AC1350: =IF(AB1350>=5,"High",IF(AB1350>=3,"Medium","Low")) -> High
A1351: 2625-TRCZQ | B1351: Female | C1351: 0 | D1351: Yes | E1351: No | F1351: 51 | G1351: No | H1351: No phone service | I1351: DSL | J1351: No | K1351: Yes | L1351: No | M1351: No | N1351: Yes | O1351: Yes | P1351: Month-to-month | Q1351: Yes | R1351: Electronic check | S1351: 49.65 | T1351: 2553.35 | U1351: No | V1351: =IF(ISNUMBER(T1351),T1351,0) -> 2553.35 | W1351: =IF(U1351="Yes",1,0) -> 0 | X1351: =IF(F1351<=12,"0-12 months",IF(F1351<=24,"13-24 months",IF(F1351<=48,"25-48 months","49-72 months"))) -> 49-72 months | Y1351: =IF(C1351=1,"Yes","No") -> No | Z1351: =COUNTIF(J1351:O1351,"Yes") -> 3 | AA1351: =S1351*W1351 -> 0 | AB1351: =(P1351="Month-to-month")+(I1351="Fiber optic")+(R1351="Electronic check")+(F1351<=12)+(M1351="No")+(J1351="No") -> 4 | AC1351: =IF(AB1351>=5,"High",IF(AB1351>=3,"Medium","Low")) -> Medium
A1352: 4102-HLENU | B1352: Female | C1352: 0 | D1352: Yes | E1352: No | F1352: 67 | G1352: Yes | H1352: Yes | I1352: DSL | J1352: Yes | K1352: Yes | L1352: Yes | M1352: No | N1352: No | O1352: No | P1352: Two year | Q1352: No | R1352: Mailed check | S1352: 65.65 | T1352: 4322.85 | U1352: No | V1352: =IF(ISNUMBER(T1352),T1352,0) -> 4322.85 | W1352: =IF(U1352="Yes",1,0) -> 0 | X1352: =IF(F1352<=12,"0-12 months",IF(F1352<=24,"13-24 months",IF(F1352<=48,"25-48 months","49-72 months"))) -> 49-72 months | Y1352: =IF(C1352=1,"Yes","No") -> No | Z1352: =COUNTIF(J1352:O1352,"Yes") -> 3 | AA1352: =S1352*W1352 -> 0 | AB1352: =(P1352="Month-to-month")+(I1352="Fiber optic")+(R1352="Electronic check")+(F1352<=12)+(M1352="No")+(J1352="No") -> 1 | AC1352: =IF(AB1352>=5,"High",IF(AB1352>=3,"Medium","Low")) -> Low
A1353: 7266-GSSJX | B1353: Male | C1353: 0 | D1353: Yes | E1353: Yes | F1353: 11 | G1353: Yes | H1353: No | I1353: No | J1353: No internet service | K1353: No internet service | L1353: No internet service | M1353: No internet service | N1353: No internet service | O1353: No internet service | P1353: Month-to-month | Q1353: Yes | R1353: Electronic check | S1353: 20.45 | T1353: 250.8 | U1353: No | V1353: =IF(ISNUMBER(T1353),T1353,0) -> 250.8 | W1353: =IF(U1353="Yes",1,0) -> 0 | X1353: =IF(F1353<=12,"0-12 months",IF(F1353<=24,"13-24 months",IF(F1353<=48,"25-48 months","49-72 months"))) -> 0-12 months | Y1353: =IF(C1353=1,"Yes","No") -> No | Z1353: =COUNTIF(J1353:O1353,"Yes") -> 0 | AA1353: =S1353*W1353 -> 0 | AB1353: =(P1353="Month-to-month")+(I1353="Fiber optic")+(R1353="Electronic check")+(F1353<=12)+(M1353="No")+(J1353="No") -> 3 | AC1353: =IF(AB1353>=5,"High",IF(AB1353>=3,"Medium","Low")) -> Medium
A1354: 7722-VJRQD | B1354: Male | C1354: 0 | D1354: Yes | E1354: Yes | F1354: 72 | G1354: No | H1354: No phone service | I1354: DSL | J1354: Yes | K1354: No | L1354: Yes | M1354: Yes | N1354: Yes | O1354: Yes | P1354: Two year | Q1354: No | R1354: Bank transfer (automatic) | S1354: 60.95 | T1354: 4549.05 | U1354: No | V1354: =IF(ISNUMBER(T1354),T1354,0) -> 4549.05 | W1354: =IF(U1354="Yes",1,0) -> 0 | X1354: =IF(F1354<=12,"0-12 months",IF(F1354<=24,"13-24 months",IF(F1354<=48,"25-48 months","49-72 months"))) -> 49-72 months | Y1354: =IF(C1354=1,"Yes","No") -> No | Z1354: =COUNTIF(J1354:O1354,"Yes") -> 5 | AA1354: =S1354*W1354 -> 0 | AB1354: =(P1354="Month-to-month")+(I1354="Fiber optic")+(R1354="Electronic check")+(F1354<=12)+(M1354="No")+(J1354="No") -> 0 | AC1354: =IF(AB1354>=5,"High",IF(AB1354>=3,"Medium","Low")) -> Low
... A3332: 8276-MQBYC | B3332: Male | C3332: 1 | D3332: No | E3332: No | F3332: 51 | G3332: Yes | H3332: Yes | I3332: Fiber optic | J3332: No | K3332: No | L3332: Yes | M3332: No | N3332: Yes | O3332: Yes | P3332: Month-to-month | Q3332: Yes | R3332: Electronic check | S3332: 97.8 | T3332: 4913.3 | U3332: Yes | V3332: =IF(ISNUMBER(T3332),T3332,0) -> 4913.3 | W3332: =IF(U3332="Yes",1,0) -> 1 | X3332: =IF(F3332<=12,"0-12 months",IF(F3332<=24,"13-24 months",IF(F3332<=48,"25-48 months","49-72 months"))) -> 49-72 months | Y3332: =IF(C3332=1,"Yes","No") -> Yes | Z3332: =COUNTIF(J3332:O3332,"Yes") -> 3 | AA3332: =S3332*W3332 -> 97.8 | AB3332: =(P3332="Month-to-month")+(I3332="Fiber optic")+(R3332="Electronic check")+(F3332<=12)+(M3332="No")+(J3332="No") -> 5 | AC3332: =IF(AB3332>=5,"High",IF(AB3332>=3,"Medium","Low")) -> High
A3333: 7644-OMVMY | B3333: Male | C3333: 0 | D3333: Yes | E3333: Yes | F3333: 0 | G3333: Yes | H3333: No | I3333: No | J3333: No internet service | K3333: No internet service | L3333: No internet service | M3333: No internet service | N3333: No internet service | O3333: No internet service | P3333: Two year | Q3333: No | R3333: Mailed check | S3333: 19.85 | U3333: No | V3333: =IF(ISNUMBER(T3333),T3333,0) -> 0 | W3333: =IF(U3333="Yes",1,0) -> 0 | X3333: =IF(F3333<=12,"0-12 months",IF(F3333<=24,"13-24 months",IF(F3333<=48,"25-48 months","49-72 months"))) -> 0-12 months | Y3333: =IF(C3333=1,"Yes","No") -> No | Z3333: =COUNTIF(J3333:O3333,"Yes") -> 0 | AA3333: =S3333*W3333 -> 0 | AB3333: =(P3333="Month-to-month")+(I3333="Fiber optic")+(R3333="Electronic check")+(F3333<=12)+(M3333="No")+(J3333="No") -> 1 | AC3333: =IF(AB3333>=5,"High",IF(AB3333>=3,"Medium","Low")) -> Low
A3334: 7593-XFKDI | B3334: Male | C3334: 0 | D3334: No | E3334: No | F3334: 1 | G3334: Yes | H3334: No | I3334: DSL | J3334: No | K3334: No | L3334: No | M3334: No | N3334: No | O3334: No | P3334: Month-to-month | Q3334: No | R3334: Mailed check | S3334: 46.3 | T3334: 46.3 | U3334: Yes | V3334: =IF(ISNUMBER(T3334),T3334,0) -> 46.3 | W3334: =IF(U3334="Yes",1,0) -> 1 | X3334: =IF(F3334<=12,"0-12 months",IF(F3334<=24,"13-24 months",IF(F3334<=48,"25-48 months","49-72 months"))) -> 0-12 months | Y3334: =IF(C3334=1,"Yes","No") -> No | Z3334: =COUNTIF(J3334:O3334,"Yes") -> 0 | AA3334: =S3334*W3334 -> 46.3 | AB3334: =(P3334="Month-to-month")+(I3334="Fiber optic")+(R3334="Electronic check")+(F3334<=12)+(M3334="No")+(J3334="No") -> 4 | AC3334: =IF(AB3334>=5,"High",IF(AB3334>=3,"Medium","Low")) -> Medium
A3335: 4573-JKNAE | B3335: Male | C3335: 0 | D3335: No | E3335: Yes | F3335: 12 | G3335: Yes | H3335: No | I3335: No | J3335: No internet service | K3335: No internet service | L3335: No internet service | M3335: No internet service | N3335: No internet service | O3335: No internet service | P3335: Two year | Q3335: No | R3335: Bank transfer (automatic) | S3335: 19.35 | T3335: 212.3 | U3335: No | V3335: =IF(ISNUMBER(T3335),T3335,0) -> 212.3 | W3335: =IF(U3335="Yes",1,0) -> 0 | X3335: =IF(F3335<=12,"0-12 months",IF(F3335<=24,"13-24 months",IF(F3335<=48,"25-48 months","49-72 months"))) -> 0-12 months | Y3335: =IF(C3335=1,"Yes","No") -> No | Z3335: =COUNTIF(J3335:O3335,"Yes") -> 0 | AA3335: =S3335*W3335 -> 0 | AB3335: =(P3335="Month-to-month")+(I3335="Fiber optic")+(R3335="Electronic check")+(F3335<=12)+(M3335="No")+(J3335="No") -> 1 | AC3335: =IF(AB3335>=5,"High",IF(AB3335>=3,"Medium","Low")) -> Low
A3336: 0337-CNPZE | B3336: Female | C3336: 0 | D3336: No | E3336: No | F3336: 41 | G3336: Yes | H3336: Yes | I3336: Fiber optic | J3336: No | K3336: Yes | L3336: Yes | M3336: No | N3336: Yes | O3336: Yes | P3336: Month-to-month | Q3336: Yes | R3336: Electronic check | S3336: 106.3 | T3336: 4443.45 | U3336: Yes | V3336: =IF(ISNUMBER(T3336),T3336,0) -> 4443.45 | W3336: =IF(U3336="Yes",1,0) -> 1 | X3336: =IF(F3336<=12,"0-12 months",IF(F3336<=24,"13-24 months",IF(F3336<=48,"25-48 months","49-72 months"))) -> 25-48 months | Y3336: =IF(C3336=1,"Yes","No") -> No | Z3336: =COUNTIF(J3336:O3336,"Yes") -> 4 | AA3336: =S3336*W3336 -> 106.3 | AB3336: =(P3336="Month-to-month")+(I3336="Fiber optic")+(R3336="Electronic check")+(F3336<=12)+(M3336="No")+(J3336="No") -> 5 | AC3336: =IF(AB3336>=5,"High",IF(AB3336>=3,"Medium","Low")) -> High
A3337: 9817-APLHW | B3337: Male | C3337: 0 | D3337: No | E3337: No | F3337: 12 | G3337: Yes | H3337: Yes | I3337: No | J3337: No internet service | K3337: No internet service | L3337: No internet service | M3337: No internet service | N3337: No internet service | O3337: No internet service | P3337: Month-to-month | Q3337: No | R3337: Electronic check | S3337: 25 | T3337: 316.2 | U3337: No | V3337: =IF(ISNUMBER(T3337),T3337,0) -> 316.2 | W3337: =IF(U3337="Yes",1,0) -> 0 | X3337: =IF(F3337<=12,"0-12 months",IF(F3337<=24,"13-24 months",IF(F3337<=48,"25-48 months","49-72 months"))) -> 0-12 months | Y3337: =IF(C3337=1,"Yes","No") -> No | Z3337: =COUNTIF(J3337:O3337,"Yes") -> 0 | AA3337: =S3337*W3337 -> 0 | AB3337: =(P3337="Month-to-month")+(I3337="Fiber optic")+(R3337="Electronic check")+(F3337<=12)+(M3337="No")+(J3337="No") -> 3 | AC3337: =IF(AB3337>=5,"High",IF(AB3337>=3,"Medium","Low")) -> Medium
A3338: 8380-MQINP | B3338: Female | C3338: 0 | D3338: Yes | E3338: Yes | F3338: 55 | G3338: Yes | H3338: No | I3338: No | J3338: No internet service | K3338: No internet service | L3338: No internet service | M3338: No internet service | N3338: No internet service | O3338: No internet service | P3338: Two year | Q3338: No | R3338: Mailed check | S3338: 20.3 | T3338: 1079.05 | U3338: No | V3338: =IF(ISNUMBER(T3338),T3338,0) -> 1079.05 | W3338: =IF(U3338="Yes",1,0) -> 0 | X3338: =IF(F3338<=12,"0-12 months",IF(F3338<=24,"13-24 months",IF(F3338<=48,"25-48 months","49-72 months"))) -> 49-72 months | Y3338: =IF(C3338=1,"Yes","No") -> No | Z3338: =COUNTIF(J3338:O3338,"Yes") -> 0 | AA3338: =S3338*W3338 -> 0 | AB3338: =(P3338="Month-to-month")+(I3338="Fiber optic")+(R3338="Electronic check")+(F3338<=12)+(M3338="No")+(J3338="No") -> 0 | AC3338: =IF(AB3338>=5,"High",IF(AB3338>=3,"Medium","Low")) -> Low
A3339: 0840-DFEZH | B3339: Female | C3339: 0 | D3339: No | E3339: No | F3339: 7 | G3339: Yes | H3339: Yes | I3339: Fiber optic | J3339: No | K3339: No | L3339: No | M3339: No | N3339: No | O3339: No | P3339: Month-to-month | Q3339: Yes | R3339: Electronic check | S3339: 75.35 | T3339: 564.65 | U3339: No | V3339: =IF(ISNUMBER(T3339),T3339,0) -> 564.65 | W3339: =IF(U3339="Yes",1,0) -> 0 | X3339: =IF(F3339<=12,"0-12 months",IF(F3339<=24,"13-24 months",IF(F3339<=48,"25-48 months","49-72 months"))) -> 0-12 months | Y3339: =IF(C3339=1,"Yes","No") -> No | Z3339: =COUNTIF(J3339:O3339,"Yes") -> 0 | AA3339: =S3339*W3339 -> 0 | AB3339: =(P3339="Month-to-month")+(I3339="Fiber optic")+(R3339="Electronic check")+(F3339<=12)+(M3339="No")+(J3339="No") -> 6 | AC3339: =IF(AB3339>=5,"High",IF(AB3339>=3,"Medium","Low")) -> High
A3340: 1513-XNPPH | B3340: Female | C3340: 0 | D3340: No | E3340: No | F3340: 12 | G3340: Yes | H3340: No | I3340: Fiber optic | J3340: No | K3340: No | L3340: Yes | M3340: Yes | N3340: No | O3340: Yes | P3340: Month-to-month | Q3340: Yes | R3340: Electronic check | S3340: 89.4 | T3340: 1095.65 | U3340: Yes | V3340: =IF(ISNUMBER(T3340),T3340,0) -> 1095.65 | W3340: =IF(U3340="Yes",1,0) -> 1 | X3340: =IF(F3340<=12,"0-12 months",IF(F3340<=24,"13-24 months",IF(F3340<=48,"25-48 months","49-72 months"))) -> 0-12 months | Y3340: =IF(C3340=1,"Yes","No") -> No | Z3340: =COUNTIF(J3340:O3340,"Yes") -> 3 | AA3340: =S3340*W3340 -> 89.4 | AB3340: =(P3340="Month-to-month")+(I3340="Fiber optic")+(R3340="Electronic check")+(F3340<=12)+(M3340="No")+(J3340="No") -> 5 | AC3340: =IF(AB3340>=5,"High",IF(AB3340>=3,"Medium","Low")) -> High
A3341: 8690-ZVLCL | B3341: Female | C3341: 0 | D3341: Yes | E3341: Yes | F3341: 68 | G3341: Yes | H3341: Yes | I3341: DSL | J3341: Yes | K3341: Yes | L3341: Yes | M3341: Yes | N3341: Yes | O3341: Yes | P3341: Two year | Q3341: No | R3341: Credit card (automatic) | S3341: 88 | T3341: 6161.9 | U3341: No | V3341: =IF(ISNUMBER(T3341),T3341,0) -> 6161.9 | W3341: =IF(U3341="Yes",1,0) -> 0 | X3341: =IF(F3341<=12,"0-12 months",IF(F3341<=24,"13-24 months",IF(F3341<=48,"25-48 months","49-72 months"))) -> 49-72 months | Y3341: =IF(C3341=1,"Yes","No") -> No | Z3341: =COUNTIF(J3341:O3341,"Yes") -> 6 | AA3341: =S3341*W3341 -> 0 | AB3341: =(P3341="Month-to-month")+(I3341="Fiber optic")+(R3341="Electronic check")+(F3341<=12)+(M3341="No")+(J3341="No") -> 0 | AC3341: =IF(AB3341>=5,"High",IF(AB3341>=3,"Medium","Low")) -> Low
A3342: 6015-VVHHE | B3342: Female | C3342: 1 | D3342: No | E3342: No | F3342: 5 | G3342: Yes | H3342: Yes | I3342: Fiber optic | J3342: No | K3342: No | L3342: No | M3342: No | N3342: Yes | O3342: No | P3342: Month-to-month | Q3342: Yes | R3342: Credit card (automatic) | S3342: 83.15 | T3342: 446.05 | U3342: Yes | V3342: =IF(ISNUMBER(T3342),T3342,0) -> 446.05 | W3342: =IF(U3342="Yes",1,0) -> 1 | X3342: =IF(F3342<=12,"0-12 months",IF(F3342<=24,"13-24 months",IF(F3342<=48,"25-48 months","49-72 months"))) -> 0-12 months | Y3342: =IF(C3342=1,"Yes","No") -> Yes | Z3342: =COUNTIF(J3342:O3342,"Yes") -> 1 | AA3342: =S3342*W3342 -> 83.15 | AB3342: =(P3342="Month-to-month")+(I3342="Fiber optic")+(R3342="Electronic check")+(F3342<=12)+(M3342="No")+(J3342="No") -> 5 | AC3342: =IF(AB3342>=5,"High",IF(AB3342>=3,"Medium","Low")) -> High
A3343: 1125-SNVCK | B3343: Female | C3343: 1 | D3343: No | E3343: No | F3343: 49 | G3343: Yes | H3343: No | I3343: DSL | J3343: No | K3343: No | L3343: No | M3343: No | N3343: No | O3343: No | P3343: Month-to-month | Q3343: No | R3343: Mailed check | S3343: 43.8 | T3343: 2106.05 | U3343: No | V3343: =IF(ISNUMBER(T3343),T3343,0) -> 2106.05 | W3343: =IF(U3343="Yes",1,0) -> 0 | X3343: =IF(F3343<=12,"0-12 months",IF(F3343<=24,"13-24 months",IF(F3343<=48,"25-48 months","49-72 months"))) -> 49-72 months | Y3343: =IF(C3343=1,"Yes","No") -> Yes | Z3343: =COUNTIF(J3343:O3343,"Yes") -> 0 | AA3343: =S3343*W3343 -> 0 | AB3343: =(P3343="Month-to-month")+(I3343="Fiber optic")+(R3343="Electronic check")+(F3343<=12)+(M3343="No")+(J3343="No") -> 3 | AC3343: =IF(AB3343>=5,"High",IF(AB3343>=3,"Medium","Low")) -> Medium
A3344: 0384-LPITE | B3344: Male | C3344: 0 | D3344: No | E3344: No | F3344: 40 | G3344: No | H3344: No phone service | I3344: DSL | J3344: Yes | K3344: Yes | L3344: Yes | M3344: No | N3344: Yes | O3344: Yes | P3344: One year | Q3344: No | R3344: Credit card (automatic) | S3344: 62.05 | T3344: 2511.55 | U3344: No | V3344: =IF(ISNUMBER(T3344),T3344,0) -> 2511.55 | W3344: =IF(U3344="Yes",1,0) -> 0 | X3344: =IF(F3344<=12,"0-12 months",IF(F3344<=24,"13-24 months",IF(F3344<=48,"25-48 months","49-72 months"))) -> 25-48 months | Y3344: =IF(C3344=1,"Yes","No") -> No | Z3344: =COUNTIF(J3344:O3344,"Yes") -> 5 | AA3344: =S3344*W3344 -> 0 | AB3344: =(P3344="Month-to-month")+(I3344="Fiber optic")+(R3344="Electronic check")+(F3344<=12)+(M3344="No")+(J3344="No") -> 1 | AC3344: =IF(AB3344>=5,"High",IF(AB3344>=3,"Medium","Low")) -> Low
A3345: 4616-EWBNJ | B3345: Female | C3345: 0 | D3345: No | E3345: No | F3345: 16 | G3345: Yes | H3345: No | I3345: No | J3345: No internet service | K3345: No internet service | L3345: No internet service | M3345: No internet service | N3345: No internet service | O3345: No internet service | P3345: One year | Q3345: No | R3345: Bank transfer (automatic) | S3345: 20.1 | T3345: 318.6 | U3345: No | V3345: =IF(ISNUMBER(T3345),T3345,0) -> 318.6 | W3345: =IF(U3345="Yes",1,0) -> 0 | X3345: =IF(F3345<=12,"0-12 months",IF(F3345<=24,"13-24 months",IF(F3345<=48,"25-48 months","49-72 months"))) -> 13-24 months | Y3345: =IF(C3345=1,"Yes","No") -> No | Z3345: =COUNTIF(J3345:O3345,"Yes") -> 0 | AA3345: =S3345*W3345 -> 0 | AB3345: =(P3345="Month-to-month")+(I3345="Fiber optic")+(R3345="Electronic check")+(F3345<=12)+(M3345="No")+(J3345="No") -> 0 | AC3345: =IF(AB3345>=5,"High",IF(AB3345>=3,"Medium","Low")) -> Low
... A3827: 3620-EHIMZ | B3827: Female | C3827: 0 | D3827: Yes | E3827: Yes | F3827: 52 | G3827: Yes | H3827: No | I3827: No | J3827: No internet service | K3827: No internet service | L3827: No internet service | M3827: No internet service | N3827: No internet service | O3827: No internet service | P3827: Two year | Q3827: No | R3827: Mailed check | S3827: 19.35 | T3827: 1031.7 | U3827: No | V3827: =IF(ISNUMBER(T3827),T3827,0) -> 1031.7 | W3827: =IF(U3827="Yes",1,0) -> 0 | X3827: =IF(F3827<=12,"0-12 months",IF(F3827<=24,"13-24 months",IF(F3827<=48,"25-48 months","49-72 months"))) -> 49-72 months | Y3827: =IF(C3827=1,"Yes","No") -> No | Z3827: =COUNTIF(J3827:O3827,"Yes") -> 0 | AA3827: =S3827*W3827 -> 0 | AB3827: =(P3827="Month-to-month")+(I3827="Fiber optic")+(R3827="Electronic check")+(F3827<=12)+(M3827="No")+(J3827="No") -> 0 | AC3827: =IF(AB3827>=5,"High",IF(AB3827>=3,"Medium","Low")) -> Low
A3828: 3213-VVOLG | B3828: Male | C3828: 0 | D3828: Yes | E3828: Yes | F3828: 0 | G3828: Yes | H3828: Yes | I3828: No | J3828: No internet service | K3828: No internet service | L3828: No internet service | M3828: No internet service | N3828: No internet service | O3828: No internet service | P3828: Two year | Q3828: No | R3828: Mailed check | S3828: 25.35 | U3828: No | V3828: =IF(ISNUMBER(T3828),T3828,0) -> 0 | W3828: =IF(U3828="Yes",1,0) -> 0 | X3828: =IF(F3828<=12,"0-12 months",IF(F3828<=24,"13-24 months",IF(F3828<=48,"25-48 months","49-72 months"))) -> 0-12 months | Y3828: =IF(C3828=1,"Yes","No") -> No | Z3828: =COUNTIF(J3828:O3828,"Yes") -> 0 | AA3828: =S3828*W3828 -> 0 | AB3828: =(P3828="Month-to-month")+(I3828="Fiber optic")+(R3828="Electronic check")+(F3828<=12)+(M3828="No")+(J3828="No") -> 1 | AC3828: =IF(AB3828>=5,"High",IF(AB3828>=3,"Medium","Low")) -> Low
A3829: 6870-ECSHE | B3829: Female | C3829: 0 | D3829: No | E3829: No | F3829: 2 | G3829: Yes | H3829: No | I3829: No | J3829: No internet service | K3829: No internet service | L3829: No internet service | M3829: No internet service | N3829: No internet service | O3829: No internet service | P3829: One year | Q3829: No | R3829: Mailed check | S3829: 20.45 | T3829: 34.8 | U3829: No | V3829: =IF(ISNUMBER(T3829),T3829,0) -> 34.8 | W3829: =IF(U3829="Yes",1,0) -> 0 | X3829: =IF(F3829<=12,"0-12 months",IF(F3829<=24,"13-24 months",IF(F3829<=48,"25-48 months","49-72 months"))) -> 0-12 months | Y3829: =IF(C3829=1,"Yes","No") -> No | Z3829: =COUNTIF(J3829:O3829,"Yes") -> 0 | AA3829: =S3829*W3829 -> 0 | AB3829: =(P3829="Month-to-month")+(I3829="Fiber optic")+(R3829="Electronic check")+(F3829<=12)+(M3829="No")+(J3829="No") -> 1 | AC3829: =IF(AB3829>=5,"High",IF(AB3829>=3,"Medium","Low")) -> Low
...

Sheet Analysis
A1: Churn drivers: what separates customers who leave from those who stay
A2: Every number is a live COUNTIFS / SUMIFS formula on the Data sheet. Lift = segment churn rate / overall churn rate.
A4: Overall | B4: Customers | C4: Churned | D4: Churn rate | E4: Monthly revenue (MRR) | F4: Lost MRR | G4: % of lost MRR | H4: Lift vs average
A5: All customers | B5: =COUNTA(Data!$A$2:$A$7044) -> 7043 | C5: =SUM(Data!$W$2:$W$7044) -> 1869 | D5: =IFERROR(C5/B5,0) -> 0.26536987 | E5: =SUM(Data!$S$2:$S$7044) -> 456116.6 | F5: =SUM(Data!$AA$2:$AA$7044) -> 139130.85 | G5: =IFERROR(F5/$F$5,0) -> 1 | H5: =IFERROR(D5/$D$5,0) -> 1
A7: Contract type
A8: Segment | B8: Customers | C8: Churned | D8: Churn rate | E8: Monthly revenue (MRR) | F8: Lost MRR | G8: % of lost MRR | H8: Lift vs average
A9: Month-to-month | B9: =COUNTIFS(Data!$P$2:$P$7044,A9) -> 3875 | C9: =COUNTIFS(Data!$P$2:$P$7044,A9,Data!$W$2:$W$7044,1) -> 1655 | D9: =IFERROR(C9/B9,0) -> 0.42709677 | E9: =SUMIFS(Data!$S$2:$S$7044,Data!$P$2:$P$7044,A9) -> 257294.15 | F9: =SUMIFS(Data!$AA$2:$AA$7044,Data!$P$2:$P$7044,A9) -> 120847.1 | G9: =IFERROR(F9/$F$5,0) -> 0.86858594 | H9: =IFERROR(D9/$D$5,0) -> 1.6094396
A10: One year | B10: =COUNTIFS(Data!$P$2:$P$7044,A10) -> 1473 | C10: =COUNTIFS(Data!$P$2:$P$7044,A10,Data!$W$2:$W$7044,1) -> 166 | D10: =IFERROR(C10/B10,0) -> 0.11269518 | E10: =SUMIFS(Data!$S$2:$S$7044,Data!$P$2:$P$7044,A10) -> 95816.6 | F10: =SUMIFS(Data!$AA$2:$AA$7044,Data!$P$2:$P$7044,A10) -> 14118.45 | G10: =IFERROR(F10/$F$5,0) -> 0.10147606 | H10: =IFERROR(D10/$D$5,0) -> 0.4246721
A11: Two year | B11: =COUNTIFS(Data!$P$2:$P$7044,A11) -> 1695 | C11: =COUNTIFS(Data!$P$2:$P$7044,A11,Data!$W$2:$W$7044,1) -> 48 | D11: =IFERROR(C11/B11,0) -> 0.028318584 | E11: =SUMIFS(Data!$S$2:$S$7044,Data!$P$2:$P$7044,A11) -> 103005.85 | F11: =SUMIFS(Data!$AA$2:$AA$7044,Data!$P$2:$P$7044,A11) -> 4165.3 | G11: =IFERROR(F11/$F$5,0) -> 0.029938004 | H11: =IFERROR(D11/$D$5,0) -> 0.10671364
A14: Tenure
A15: Segment | B15: Customers | C15: Churned | D15: Churn rate | E15: Monthly revenue (MRR) | F15: Lost MRR | G15: % of lost MRR | H15: Lift vs average
A16: 0-12 months | B16: =COUNTIFS(Data!$X$2:$X$7044,A16) -> 2186 | C16: =COUNTIFS(Data!$X$2:$X$7044,A16,Data!$W$2:$W$7044,1) -> 1037 | D16: =IFERROR(C16/B16,0) -> 0.47438243 | E16: =SUMIFS(Data!$S$2:$S$7044,Data!$X$2:$X$7044,A16) -> 122629.75 | F16: =SUMIFS(Data!$AA$2:$AA$7044,Data!$X$2:$X$7044,A16) -> 68954.25 | G16: =IFERROR(F16/$F$5,0) -> 0.49560719 | H16: =IFERROR(D16/$D$5,0) -> 1.7876273
A17: 13-24 months | B17: =COUNTIFS(Data!$X$2:$X$7044,A17) -> 1024 | C17: =COUNTIFS(Data!$X$2:$X$7044,A17,Data!$W$2:$W$7044,1) -> 294 | D17: =IFERROR(C17/B17,0) -> 0.28710938 | E17: =SUMIFS(Data!$S$2:$S$7044,Data!$X$2:$X$7044,A17) -> 62829.85 | F17: =SUMIFS(Data!$AA$2:$AA$7044,Data!$X$2:$X$7044,A17) -> 23081.65 | G17: =IFERROR(F17/$F$5,0) -> 0.16589886 | H17: =IFERROR(D17/$D$5,0) -> 1.0819215
A18: 25-48 months | B18: =COUNTIFS(Data!$X$2:$X$7044,A18) -> 1594 | C18: =COUNTIFS(Data!$X$2:$X$7044,A18,Data!$W$2:$W$7044,1) -> 325 | D18: =IFERROR(C18/B18,0) -> 0.20388959 | E18: =SUMIFS(Data!$S$2:$S$7044,Data!$X$2:$X$7044,A18) -> 105093.3 | F18: =SUMIFS(Data!$AA$2:$AA$7044,Data!$X$2:$X$7044,A18) -> 27462.5 | G18: =IFERROR(F18/$F$5,0) -> 0.19738613 | H18: =IFERROR(D18/$D$5,0) -> 0.76832229
A19: 49-72 months | B19: =COUNTIFS(Data!$X$2:$X$7044,A19) -> 2239 | C19: =COUNTIFS(Data!$X$2:$X$7044,A19,Data!$W$2:$W$7044,1) -> 213 | D19: =IFERROR(C19/B19,0) -> 0.095131755 | E19: =SUMIFS(Data!$S$2:$S$7044,Data!$X$2:$X$7044,A19) -> 165563.7 | F19: =SUMIFS(Data!$AA$2:$AA$7044,Data!$X$2:$X$7044,A19) -> 19632.45 | G19: =IFERROR(F19/$F$5,0) -> 0.14110781 | H19: =IFERROR(D19/$D$5,0) -> 0.3584874
A22: Internet service
A23: Segment | B23: Customers | C23: Churned | D23: Churn rate | E23: Monthly revenue (MRR) | F23: Lost MRR | G23: % of lost MRR | H23: Lift vs average
A24: Fiber optic | B24: =COUNTIFS(Data!$I$2:$I$7044,A24) -> 3096 | C24: =COUNTIFS(Data!$I$2:$I$7044,A24,Data!$W$2:$W$7044,1) -> 1297 | D24: =IFERROR(C24/B24,0) -> 0.41892765 | E24: =SUMIFS(Data!$S$2:$S$7044,Data!$I$2:$I$7044,A24) -> 283284.4 | F24: =SUMIFS(Data!$AA$2:$AA$7044,Data!$I$2:$I$7044,A24) -> 114300.05 | G24: =IFERROR(F24/$F$5,0) -> 0.82152916 | H24: =IFERROR(D24/$D$5,0) -> 1.5786557
A25: DSL | B25: =COUNTIFS(Data!$I$2:$I$7044,A25) -> 2421 | C25: =COUNTIFS(Data!$I$2:$I$7044,A25,Data!$W$2:$W$7044,1) -> 459 | D25: =IFERROR(C25/B25,0) -> 0.18959108 | E25: =SUMIFS(Data!$S$2:$S$7044,Data!$I$2:$I$7044,A25) -> 140665.35 | F25: =SUMIFS(Data!$AA$2:$AA$7044,Data!$I$2:$I$7044,A25) -> 22529.2 | G25: =IFERROR(F25/$F$5,0) -> 0.16192814 | H25: =IFERROR(D25/$D$5,0) -> 0.71444086
A26: No | B26: =COUNTIFS(Data!$I$2:$I$7044,A26) -> 1526 | C26: =COUNTIFS(Data!$I$2:$I$7044,A26,Data!$W$2:$W$7044,1) -> 113 | D26: =IFERROR(C26/B26,0) -> 0.074049803 | E26: =SUMIFS(Data!$S$2:$S$7044,Data!$I$2:$I$7044,A26) -> 32166.85 | F26: =SUMIFS(Data!$AA$2:$AA$7044,Data!$I$2:$I$7044,A26) -> 2301.6 | G26: =IFERROR(F26/$F$5,0) -> 0.016542701 | H26: =IFERROR(D26/$D$5,0) -> 0.27904375
A29: Payment method
A30: Segment | B30: Customers | C30: Churned | D30: Churn rate | E30: Monthly revenue (MRR) | F30: Lost MRR | G30: % of lost MRR | H30: Lift vs average
A31: Electronic check | B31: =COUNTIFS(Data!$R$2:$R$7044,A31) -> 2365 | C31: =COUNTIFS(Data!$R$2:$R$7044,A31,Data!$W$2:$W$7044,1) -> 1071 | D31: =IFERROR(C31/B31,0) -> 0.45285412 | E31: =SUMIFS(Data!$S$2:$S$7044,Data!$R$2:$R$7044,A31) -> 180345 | F31: =SUMIFS(Data!$AA$2:$AA$7044,Data!$R$2:$R$7044,A31) -> 84288.75 | G31: =IFERROR(F31/$F$5,0) -> 0.60582358 | H31: =IFERROR(D31/$D$5,0) -> 1.7065017
A32: Mailed check | B32: =COUNTIFS(Data!$R$2:$R$7044,A32) -> 1612 | C32: =COUNTIFS(Data!$R$2:$R$7044,A32,Data!$W$2:$W$7044,1) -> 308 | D32: =IFERROR(C32/B32,0) -> 0.191067 | E32: =SUMIFS(Data!$S$2:$S$7044,Data!$R$2:$R$7044,A32) -> 70794.3 | F32: =SUMIFS(Data!$AA$2:$AA$7044,Data!$R$2:$R$7044,A32) -> 16803.6 | G32: =IFERROR(F32/$F$5,0) -> 0.12077551 | H32: =IFERROR(D32/$D$5,0) -> 0.7200026
A33: Bank transfer (automatic) | B33: =COUNTIFS(Data!$R$2:$R$7044,A33) -> 1544 | C33: =COUNTIFS(Data!$R$2:$R$7044,A33,Data!$W$2:$W$7044,1) -> 258 | D33: =IFERROR(C33/B33,0) -> 0.16709845 | E33: =SUMIFS(Data!$S$2:$S$7044,Data!$R$2:$R$7044,A33) -> 103745.45 | F33: =SUMIFS(Data!$AA$2:$AA$7044,Data!$R$2:$R$7044,A33) -> 20091.9 | G33: =IFERROR(F33/$F$5,0) -> 0.1444101 | H33: =IFERROR(D33/$D$5,0) -> 0.6296813
A34: Credit card (automatic) | B34: =COUNTIFS(Data!$R$2:$R$7044,A34) -> 1522 | C34: =COUNTIFS(Data!$R$2:$R$7044,A34,Data!$W$2:$W$7044,1) -> 232 | D34: =IFERROR(C34/B34,0) -> 0.15243101 | E34: =SUMIFS(Data!$S$2:$S$7044,Data!$R$2:$R$7044,A34) -> 101231.85 | F34: =SUMIFS(Data!$AA$2:$AA$7044,Data!$R$2:$R$7044,A34) -> 17946.6 | G34: =IFERROR(F34/$F$5,0) -> 0.1289908 | H34: =IFERROR(D34/$D$5,0) -> 0.57440964
A37: Tech support
A38: Segment | B38: Customers | C38: Churned | D38: Churn rate | E38: Monthly revenue (MRR) | F38: Lost MRR | G38: % of lost MRR | H38: Lift vs average
A39: No | B39: =COUNTIFS(Data!$M$2:$M$7044,A39) -> 3473 | C39: =COUNTIFS(Data!$M$2:$M$7044,A39,Data!$W$2:$W$7044,1) -> 1446 | D39: =IFERROR(C39/B39,0) -> 0.41635474 | E39: =SUMIFS(Data!$S$2:$S$7044,Data!$M$2:$M$7044,A39) -> 259039.55 | F39: =SUMIFS(Data!$AA$2:$AA$7044,Data!$M$2:$M$7044,A39) -> 110709.8 | G39: =IFERROR(F39/$F$5,0) -> 0.79572431 | H39: =IFERROR(D39/$D$5,0) -> 1.5689601
A40: Yes | B40: =COUNTIFS(Data!$M$2:$M$7044,A40) -> 2044 | C40: =COUNTIFS(Data!$M$2:$M$7044,A40,Data!$W$2:$W$7044,1) -> 310 | D40: =IFERROR(C40/B40,0) -> 0.15166341 | E40: =SUMIFS(Data!$S$2:$S$7044,Data!$M$2:$M$7044,A40) -> 164910.2 | F40: =SUMIFS(Data!$AA$2:$AA$7044,Data!$M$2:$M$7044,A40) -> 26119.45 | G40: =IFERROR(F40/$F$5,0) -> 0.18773299 | H40: =IFERROR(D40/$D$5,0) -> 0.57151705
A41: No internet service | B41: =COUNTIFS(Data!$M$2:$M$7044,A41) -> 1526 | C41: =COUNTIFS(Data!$M$2:$M$7044,A41,Data!$W$2:$W$7044,1) -> 113 | D41: =IFERROR(C41/B41,0) -> 0.074049803 | E41: =SUMIFS(Data!$S$2:$S$7044,Data!$M$2:$M$7044,A41) -> 32166.85 | F41: =SUMIFS(Data!$AA$2:$AA$7044,Data!$M$2:$M$7044,A41) -> 2301.6 | G41: =IFERROR(F41/$F$5,0) -> 0.016542701 | H41: =IFERROR(D41/$D$5,0) -> 0.27904375
A44: Online security
A45: Segment | B45: Customers | C45: Churned | D45: Churn rate | E45: Monthly revenue (MRR) | F45: Lost MRR | G45: % of lost MRR | H45: Lift vs average
A46: No | B46: =COUNTIFS(Data!$J$2:$J$7044,A46) -> 3498 | C46: =COUNTIFS(Data!$J$2:$J$7044,A46,Data!$W$2:$W$7044,1) -> 1461 | D46: =IFERROR(C46/B46,0) -> 0.41766724 | E46: =SUMIFS(Data!$S$2:$S$7044,Data!$J$2:$J$7044,A46) -> 264774.35 | F46: =SUMIFS(Data!$AA$2:$AA$7044,Data!$J$2:$J$7044,A46) -> 112762.75 | G46: =IFERROR(F46/$F$5,0) -> 0.81047985 | H46: =IFERROR(D46/$D$5,0) -> 1.573906
A47: Yes | B47: =COUNTIFS(Data!$J$2:$J$7044,A47) -> 2019 | C47: =COUNTIFS(Data!$J$2:$J$7044,A47,Data!$W$2:$W$7044,1) -> 295 | D47: =IFERROR(C47/B47,0) -> 0.14611194 | E47: =SUMIFS(Data!$S$2:$S$7044,Data!$J$2:$J$7044,A47) -> 159175.4 | F47: =SUMIFS(Data!$AA$2:$AA$7044,Data!$J$2:$J$7044,A47) -> 24066.5 | G47: =IFERROR(F47/$F$5,0) -> 0.17297745 | H47: =IFERROR(D47/$D$5,0) -> 0.55059731
A48: No internet service | B48: =COUNTIFS(Data!$J$2:$J$7044,A48) -> 1526 | C48: =COUNTIFS(Data!$J$2:$J$7044,A48,Data!$W$2:$W$7044,1) -> 113 | D48: =IFERROR(C48/B48,0) -> 0.074049803 | E48: =SUMIFS(Data!$S$2:$S$7044,Data!$J$2:$J$7044,A48) -> 32166.85 | F48: =SUMIFS(Data!$AA$2:$AA$7044,Data!$J$2:$J$7044,A48) -> 2301.6 | G48: =IFERROR(F48/$F$5,0) -> 0.016542701 | H48: =IFERROR(D48/$D$5,0) -> 0.27904375
A51: Senior citizen
A52: Segment | B52: Customers | C52: Churned | D52: Churn rate | E52: Monthly revenue (MRR) | F52: Lost MRR | G52: % of lost MRR | H52: Lift vs average
A53: Yes | B53: =COUNTIFS(Data!$Y$2:$Y$7044,A53) -> 1142 | C53: =COUNTIFS(Data!$Y$2:$Y$7044,A53,Data!$W$2:$W$7044,1) -> 476 | D53: =IFERROR(C53/B53,0) -> 0.41681261 | E53: =SUMIFS(Data!$S$2:$S$7044,Data!$Y$2:$Y$7044,A53) -> 91154.85 | F53: =SUMIFS(Data!$AA$2:$AA$7044,Data!$Y$2:$Y$7044,A53) -> 38419.6 | G53: =IFERROR(F53/$F$5,0) -> 0.27614005 | H53: =IFERROR(D53/$D$5,0) -> 1.5706855
A54: No | B54: =COUNTIFS(Data!$Y$2:$Y$7044,A54) -> 5901 | C54: =COUNTIFS(Data!$Y$2:$Y$7044,A54,Data!$W$2:$W$7044,1) -> 1393 | D54: =IFERROR(C54/B54,0) -> 0.23606168 | E54: =SUMIFS(Data!$S$2:$S$7044,Data!$Y$2:$Y$7044,A54) -> 364961.75 | F54: =SUMIFS(Data!$AA$2:$AA$7044,Data!$Y$2:$Y$7044,A54) -> 100711.25 | G54: =IFERROR(F54/$F$5,0) -> 0.72385995 | H54: =IFERROR(D54/$D$5,0) -> 0.88955722
A57: Paperless billing
A58: Segment | B58: Customers | C58: Churned | D58: Churn rate | E58: Monthly revenue (MRR) | F58: Lost MRR | G58: % of lost MRR | H58: Lift vs average
A59: Yes | B59: =COUNTIFS(Data!$Q$2:$Q$7044,A59) -> 4171 | C59: =COUNTIFS(Data!$Q$2:$Q$7044,A59,Data!$W$2:$W$7044,1) -> 1400 | D59: =IFERROR(C59/B59,0) -> 0.33565092 | E59: =SUMIFS(Data!$S$2:$S$7044,Data!$Q$2:$Q$7044,A59) -> 306792.8 | F59: =SUMIFS(Data!$AA$2:$AA$7044,Data!$Q$2:$Q$7044,A59) -> 109510 | G59: =IFERROR(F59/$F$5,0) -> 0.78710078 | H59: =IFERROR(D59/$D$5,0) -> 1.2648419
A60: No | B60: =COUNTIFS(Data!$Q$2:$Q$7044,A60) -> 2872 | C60: =COUNTIFS(Data!$Q$2:$Q$7044,A60,Data!$W$2:$W$7044,1) -> 469 | D60: =IFERROR(C60/B60,0) -> 0.16330084 | E60: =SUMIFS(Data!$S$2:$S$7044,Data!$Q$2:$Q$7044,A60) -> 149323.8 | F60: =SUMIFS(Data!$AA$2:$AA$7044,Data!$Q$2:$Q$7044,A60) -> 29620.85 | G60: =IFERROR(F60/$F$5,0) -> 0.21289922 | H60: =IFERROR(D60/$D$5,0) -> 0.61537067
A63: Add-on services (internet customers only)
A64: Segment | B64: Customers | C64: Churned | D64: Churn rate | E64: Monthly revenue (MRR) | F64: Lost MRR | G64: % of lost MRR | H64: Lift vs average
A65: 0 | B65: =COUNTIFS(Data!$Z$2:$Z$7044,A65,Data!$I$2:$I$7044,"<>No") -> 693 | C65: =COUNTIFS(Data!$Z$2:$Z$7044,A65,Data!$W$2:$W$7044,1,Data!$I$2:$I$7044,"<>No") -> 362 | D65: =IFERROR(C65/B65,0) -> 0.52236652 | E65: =SUMIFS(Data!$S$2:$S$7044,Data!$Z$2:$Z$7044,A65,Data!$I$2:$I$7044,"<>No") -> 40600.6 | F65: =SUMIFS(Data!$AA$2:$AA$7044,Data!$Z$2:$Z$7044,A65,Data!$I$2:$I$7044,"<>No") -> 22215.25 | G65: =IFERROR(F65/$F$5,0) -> 0.15967163 | H65: =IFERROR(D65/$D$5,0) -> 1.968447
A66: 1 | B66: =COUNTIFS(Data!$Z$2:$Z$7044,A66,Data!$I$2:$I$7044,"<>No") -> 966 | C66: =COUNTIFS(Data!$Z$2:$Z$7044,A66,Data!$W$2:$W$7044,1,Data!$I$2:$I$7044,"<>No") -> 442 | D66: =IFERROR(C66/B66,0) -> 0.45755694 | E66: =SUMIFS(Data!$S$2:$S$7044,Data!$Z$2:$Z$7044,A66,Data!$I$2:$I$7044,"<>No") -> 63344.75 | F66: =SUMIFS(Data!$AA$2:$AA$7044,Data!$Z$2:$Z$7044,A66,Data!$I$2:$I$7044,"<>No") -> 30805.55 | G66: =IFERROR(F66/$F$5,0) -> 0.22141423 | H66: =IFERROR(D66/$D$5,0) -> 1.7242234
A67: 2 | B67: =COUNTIFS(Data!$Z$2:$Z$7044,A67,Data!$I$2:$I$7044,"<>No") -> 1033 | C67: =COUNTIFS(Data!$Z$2:$Z$7044,A67,Data!$W$2:$W$7044,1,Data!$I$2:$I$7044,"<>No") -> 370 | D67: =IFERROR(C67/B67,0) -> 0.35818006 | E67: =SUMIFS(Data!$S$2:$S$7044,Data!$Z$2:$Z$7044,A67,Data!$I$2:$I$7044,"<>No") -> 74807.25 | F67: =SUMIFS(Data!$AA$2:$AA$7044,Data!$Z$2:$Z$7044,A67,Data!$I$2:$I$7044,"<>No") -> 29476.2 | G67: =IFERROR(F67/$F$5,0) -> 0.21185956 | H67: =IFERROR(D67/$D$5,0) -> 1.349739
A68: 3 | B68: =COUNTIFS(Data!$Z$2:$Z$7044,A68,Data!$I$2:$I$7044,"<>No") -> 1118 | C68: =COUNTIFS(Data!$Z$2:$Z$7044,A68,Data!$W$2:$W$7044,1,Data!$I$2:$I$7044,"<>No") -> 306 | D68: =IFERROR(C68/B68,0) -> 0.27370304 | E68: =SUMIFS(Data!$S$2:$S$7044,Data!$Z$2:$Z$7044,A68,Data!$I$2:$I$7044,"<>No") -> 89563.55 | F68: =SUMIFS(Data!$AA$2:$AA$7044,Data!$Z$2:$Z$7044,A68,Data!$I$2:$I$7044,"<>No") -> 27134.8 | G68: =IFERROR(F68/$F$5,0) -> 0.19503079 | H68: =IFERROR(D68/$D$5,0) -> 1.0314021
A69: 4 | B69: =COUNTIFS(Data!$Z$2:$Z$7044,A69,Data!$I$2:$I$7044,"<>No") -> 852 | C69: =COUNTIFS(Data!$Z$2:$Z$7044,A69,Data!$W$2:$W$7044,1,Data!$I$2:$I$7044,"<>No") -> 190 | D69: =IFERROR(C69/B69,0) -> 0.22300469 | E69: =SUMIFS(Data!$S$2:$S$7044,Data!$Z$2:$Z$7044,A69,Data!$I$2:$I$7044,"<>No") -> 74781.35 | F69: =SUMIFS(Data!$AA$2:$AA$7044,Data!$Z$2:$Z$7044,A69,Data!$I$2:$I$7044,"<>No") -> 18364.3 | G69: =IFERROR(F69/$F$5,0) -> 0.13199301 | H69: =IFERROR(D69/$D$5,0) -> 0.84035424
A70: 5 | B70: =COUNTIFS(Data!$Z$2:$Z$7044,A70,Data!$I$2:$I$7044,"<>No") -> 571 | C70: =COUNTIFS(Data!$Z$2:$Z$7044,A70,Data!$W$2:$W$7044,1,Data!$I$2:$I$7044,"<>No") -> 71 | D70: =IFERROR(C70/B70,0) -> 0.12434326 | E70: =SUMIFS(Data!$S$2:$S$7044,Data!$Z$2:$Z$7044,A70,Data!$I$2:$I$7044,"<>No") -> 52632.5 | F70: =SUMIFS(Data!$AA$2:$AA$7044,Data!$Z$2:$Z$7044,A70,Data!$I$2:$I$7044,"<>No") -> 7169.55 | G70: =IFERROR(F70/$F$5,0) -> 0.051530987 | H70: =IFERROR(D70/$D$5,0) -> 0.46856584
A71: 6 | B71: =COUNTIFS(Data!$Z$2:$Z$7044,A71,Data!$I$2:$I$7044,"<>No") -> 284 | C71: =COUNTIFS(Data!$Z$2:$Z$7044,A71,Data!$W$2:$W$7044,1,Data!$I$2:$I$7044,"<>No") -> 15 | D71: =IFERROR(C71/B71,0) -> 0.052816901 | E71: =SUMIFS(Data!$S$2:$S$7044,Data!$Z$2:$Z$7044,A71,Data!$I$2:$I$7044,"<>No") -> 28219.75 | F71: =SUMIFS(Data!$AA$2:$AA$7044,Data!$Z$2:$Z$7044,A71,Data!$I$2:$I$7044,"<>No") -> 1663.6 | G71: =IFERROR(F71/$F$5,0) -> 0.011957089 | H71: =IFERROR(D71/$D$5,0) -> 0.19903127
A74: Risk level
A75: Segment | B75: Customers | C75: Churned | D75: Churn rate | E75: Monthly revenue (MRR) | F75: Lost MRR | G75: % of lost MRR | H75: Lift vs average
A76: High | B76: =COUNTIFS(Data!$AC$2:$AC$7044,A76) -> 1485 | C76: =COUNTIFS(Data!$AC$2:$AC$7044,A76,Data!$W$2:$W$7044,1) -> 952 | D76: =IFERROR(C76/B76,0) -> 0.64107744 | E76: =SUMIFS(Data!$S$2:$S$7044,Data!$AC$2:$AC$7044,A76) -> 117657.45 | F76: =SUMIFS(Data!$AA$2:$AA$7044,Data!$AC$2:$AC$7044,A76) -> 75817.75 | G76: =IFERROR(F76/$F$5,0) -> 0.54493845 | H76: =IFERROR(D76/$D$5,0) -> 2.4157883
A77: Medium | B77: =COUNTIFS(Data!$AC$2:$AC$7044,A77) -> 2021 | C77: =COUNTIFS(Data!$AC$2:$AC$7044,A77,Data!$W$2:$W$7044,1) -> 649 | D77: =IFERROR(C77/B77,0) -> 0.32112815 | E77: =SUMIFS(Data!$S$2:$S$7044,Data!$AC$2:$AC$7044,A77) -> 149438.15 | F77: =SUMIFS(Data!$AA$2:$AA$7044,Data!$AC$2:$AC$7044,A77) -> 48157.95 | G77: =IFERROR(F77/$F$5,0) -> 0.34613423 | H77: =IFERROR(D77/$D$5,0) -> 1.2101154
A78: Low | B78: =COUNTIFS(Data!$AC$2:$AC$7044,A78) -> 3537 | C78: =COUNTIFS(Data!$AC$2:$AC$7044,A78,Data!$W$2:$W$7044,1) -> 268 | D78: =IFERROR(C78/B78,0) -> 0.075770427 | E78: =SUMIFS(Data!$S$2:$S$7044,Data!$AC$2:$AC$7044,A78) -> 189021 | F78: =SUMIFS(Data!$AA$2:$AA$7044,Data!$AC$2:$AC$7044,A78) -> 15155.15 | G78: =IFERROR(F78/$F$5,0) -> 0.10892732 | H78: =IFERROR(D78/$D$5,0) -> 0.28552762

Sheet Stats_Tests
A1: Is each driver real or chance? Chi-square tests in Excel
A2: CHITEST compares observed counts with the counts expected if churn were unrelated to the segment. p < 0.05 means the difference is very unlikely to be chance. It shows association, not cause.
A4: Driver | B4: p-value | C4: Significant at 5%?
A5: Contract type | B5: =CHITEST(B18:C20,E18:F20) -> 5.8630383e-258 | C5: =IF(B5<0.05,"Yes","No") -> Yes
A6: Tenure | B6: =CHITEST(B26:C29,E26:F29) -> 2.9437704e-185 | C6: =IF(B6<0.05,"Yes","No") -> Yes
A7: Internet service | B7: =CHITEST(B35:C37,E35:F37) -> 9.5717882e-160 | C7: =IF(B7<0.05,"Yes","No") -> Yes
A8: Payment method | B8: =CHITEST(B43:C46,E43:F46) -> 3.6823547e-140 | C8: =IF(B8<0.05,"Yes","No") -> Yes
A9: Tech support | B9: =CHITEST(B52:C54,E52:F54) -> 1.443084e-180 | C9: =IF(B9<0.05,"Yes","No") -> Yes
A10: Online security | B10: =CHITEST(B60:C62,E60:F62) -> 2.6611496e-185 | C10: =IF(B10<0.05,"Yes","No") -> Yes
A11: Senior citizen | B11: =CHITEST(B68:C69,E68:F69) -> 9.4779035e-37 | C11: =IF(B11<0.05,"Yes","No") -> Yes
A12: Paperless billing | B12: =CHITEST(B75:C76,E75:F76) -> 2.6145974e-58 | C12: =IF(B12<0.05,"Yes","No") -> Yes
A16: Contract type
A17: Segment | B17: Churned (observed) | C17: Stayed (observed) | D17: Row total | E17: Churned (expected) | F17: Stayed (expected)
A18: =Analysis!A9 -> Month-to-month | B18: =Analysis!C9 -> 1655 | C18: =Analysis!B9-Analysis!C9 -> 2220 | D18: =B18+C18 -> 3875 | E18: =D18*B$21/D$21 -> 1028.3082 | F18: =D18*C$21/D$21 -> 2846.6918
A19: =Analysis!A10 -> One year | B19: =Analysis!C10 -> 166 | C19: =Analysis!B10-Analysis!C10 -> 1307 | D19: =B19+C19 -> 1473 | E19: =D19*B$21/D$21 -> 390.88982 | F19: =D19*C$21/D$21 -> 1082.1102
A20: =Analysis!A11 -> Two year | B20: =Analysis!C11 -> 48 | C20: =Analysis!B11-Analysis!C11 -> 1647 | D20: =B20+C20 -> 1695 | E20: =D20*B$21/D$21 -> 449.80193 | F20: =D20*C$21/D$21 -> 1245.1981
A21: Total | B21: =SUM(B18:B20) -> 1869 | C21: =SUM(C18:C20) -> 5174 | D21: =SUM(D18:D20) -> 7043
A24: Tenure
A25: Segment | B25: Churned (observed) | C25: Stayed (observed) | D25: Row total | E25: Churned (expected) | F25: Stayed (expected)
A26: =Analysis!A16 -> 0-12 months | B26: =Analysis!C16 -> 1037 | C26: =Analysis!B16-Analysis!C16 -> 1149 | D26: =B26+C26 -> 2186 | E26: =D26*B$30/D$30 -> 580.09854 | F26: =D26*C$30/D$30 -> 1605.9015
A27: =Analysis!A17 -> 13-24 months | B27: =Analysis!C17 -> 294 | C27: =Analysis!B17-Analysis!C17 -> 730 | D27: =B27+C27 -> 1024 | E27: =D27*B$30/D$30 -> 271.73875 | F27: =D27*C$30/D$30 -> 752.26125
A28: =Analysis!A18 -> 25-48 months | B28: =Analysis!C18 -> 325 | C28: =Analysis!B18-Analysis!C18 -> 1269 | D28: =B28+C28 -> 1594 | E28: =D28*B$30/D$30 -> 422.99957 | F28: =D28*C$30/D$30 -> 1171.0004
A29: =Analysis!A19 -> 49-72 months | B29: =Analysis!C19 -> 213 | C29: =Analysis!B19-Analysis!C19 -> 2026 | D29: =B29+C29 -> 2239 | E29: =D29*B$30/D$30 -> 594.16314 | F29: =D29*C$30/D$30 -> 1644.8369
A30: Total | B30: =SUM(B26:B29) -> 1869 | C30: =SUM(C26:C29) -> 5174 | D30: =SUM(D26:D29) -> 7043
A33: Internet service
A34: Segment | B34: Churned (observed) | C34: Stayed (observed) | D34: Row total | E34: Churned (expected) | F34: Stayed (expected)
A35: =Analysis!A24 -> Fiber optic | B35: =Analysis!C24 -> 1297 | C35: =Analysis!B24-Analysis!C24 -> 1799 | D35: =B35+C35 -> 3096 | E35: =D35*B$38/D$38 -> 821.58512 | F35: =D35*C$38/D$38 -> 2274.4149
A36: =Analysis!A25 -> DSL | B36: =Analysis!C25 -> 459 | C36: =Analysis!B25-Analysis!C25 -> 1962 | D36: =B36+C36 -> 2421 | E36: =D36*B$38/D$38 -> 642.46046 | F36: =D36*C$38/D$38 -> 1778.5395
A37: =Analysis!A26 -> No | B37: =Analysis!C26 -> 113 | C37: =Analysis!B26-Analysis!C26 -> 1413 | D37: =B37+C37 -> 1526 | E37: =D37*B$38/D$38 -> 404.95442 | F37: =D37*C$38/D$38 -> 1121.0456
A38: Total | B38: =SUM(B35:B37) -> 1869 | C38: =SUM(C35:C37) -> 5174 | D38: =SUM(D35:D37) -> 7043
A41: Payment method
A42: Segment | B42: Churned (observed) | C42: Stayed (observed) | D42: Row total | E42: Churned (expected) | F42: Stayed (expected)
A43: =Analysis!A31 -> Electronic check | B43: =Analysis!C31 -> 1071 | C43: =Analysis!B31-Analysis!C31 -> 1294 | D43: =B43+C43 -> 2365 | E43: =D43*B$47/D$47 -> 627.59974 | F43: =D43*C$47/D$47 -> 1737.4003
A44: =Analysis!A32 -> Mailed check | B44: =Analysis!C32 -> 308 | C44: =Analysis!B32-Analysis!C32 -> 1304 | D44: =B44+C44 -> 1612 | E44: =D44*B$47/D$47 -> 427.77623 | F44: =D44*C$47/D$47 -> 1184.2238
A45: =Analysis!A33 -> Bank transfer (automatic) | B45: =Analysis!C33 -> 258 | C45: =Analysis!B33-Analysis!C33 -> 1286 | D45: =B45+C45 -> 1544 | E45: =D45*B$47/D$47 -> 409.73108 | F45: =D45*C$47/D$47 -> 1134.2689
A46: =Analysis!A34 -> Credit card (automatic) | B46: =Analysis!C34 -> 232 | C46: =Analysis!B34-Analysis!C34 -> 1290 | D46: =B46+C46 -> 1522 | E46: =D46*B$47/D$47 -> 403.89294 | F46: =D46*C$47/D$47 -> 1118.1071
A47: Total | B47: =SUM(B43:B46) -> 1869 | C47: =SUM(C43:C46) -> 5174 | D47: =SUM(D43:D46) -> 7043
A50: Tech support
A51: Segment | B51: Churned (observed) | C51: Stayed (observed) | D51: Row total | E51: Churned (expected) | F51: Stayed (expected)
A52: =Analysis!A39 -> No | B52: =Analysis!C39 -> 1446 | C52: =Analysis!B39-Analysis!C39 -> 2027 | D52: =B52+C52 -> 3473 | E52: =D52*B$55/D$55 -> 921.62956 | F52: =D52*C$55/D$55 -> 2551.3704
A53: =Analysis!A40 -> Yes | B53: =Analysis!C40 -> 310 | C53: =Analysis!B40-Analysis!C40 -> 1734 | D53: =B53+C53 -> 2044 | E53: =D53*B$55/D$55 -> 542.41602 | F53: =D53*C$55/D$55 -> 1501.584
A54: =Analysis!A41 -> No internet service | B54: =Analysis!C41 -> 113 | C54: =Analysis!B41-Analysis!C41 -> 1413 | D54: =B54+C54 -> 1526 | E54: =D54*B$55/D$55 -> 404.95442 | F54: =D54*C$55/D$55 -> 1121.0456
A55: Total | B55: =SUM(B52:B54) -> 1869 | C55: =SUM(C52:C54) -> 5174 | D55: =SUM(D52:D54) -> 7043
A58: Online security
A59: Segment | B59: Churned (observed) | C59: Stayed (observed) | D59: Row total | E59: Churned (expected) | F59: Stayed (expected)
A60: =Analysis!A46 -> No | B60: =Analysis!C46 -> 1461 | C60: =Analysis!B46-Analysis!C46 -> 2037 | D60: =B60+C60 -> 3498 | E60: =D60*B$63/D$63 -> 928.26381 | F60: =D60*C$63/D$63 -> 2569.7362
A61: =Analysis!A47 -> Yes | B61: =Analysis!C47 -> 295 | C61: =Analysis!B47-Analysis!C47 -> 1724 | D61: =B61+C61 -> 2019 | E61: =D61*B$63/D$63 -> 535.78177 | F61: =D61*C$63/D$63 -> 1483.2182
A62: =Analysis!A48 -> No internet service | B62: =Analysis!C48 -> 113 | C62: =Analysis!B48-Analysis!C48 -> 1413 | D62: =B62+C62 -> 1526 | E62: =D62*B$63/D$63 -> 404.95442 | F62: =D62*C$63/D$63 -> 1121.0456
A63: Total | B63: =SUM(B60:B62) -> 1869 | C63: =SUM(C60:C62) -> 5174 | D63: =SUM(D60:D62) -> 7043
A66: Senior citizen
A67: Segment | B67: Churned (observed) | C67: Stayed (observed) | D67: Row total | E67: Churned (expected) | F67: Stayed (expected)
A68: =Analysis!A53 -> Yes | B68: =Analysis!C53 -> 476 | C68: =Analysis!B53-Analysis!C53 -> 666 | D68: =B68+C68 -> 1142 | E68: =D68*B$70/D$70 -> 303.05239 | F68: =D68*C$70/D$70 -> 838.94761
A69: =Analysis!A54 -> No | B69: =Analysis!C54 -> 1393 | C69: =Analysis!B54-Analysis!C54 -> 4508 | D69: =B69+C69 -> 5901 | E69: =D69*B$70/D$70 -> 1565.9476 | F69: =D69*C$70/D$70 -> 4335.0524
A70: Total | B70: =SUM(B68:B69) -> 1869 | C70: =SUM(C68:C69) -> 5174 | D70: =SUM(D68:D69) -> 7043
A73: Paperless billing
A74: Segment | B74: Churned (observed) | C74: Stayed (observed) | D74: Row total | E74: Churned (expected) | F74: Stayed (expected)
A75: =Analysis!A59 -> Yes | B75: =Analysis!C59 -> 1400 | C75: =Analysis!B59-Analysis!C59 -> 2771 | D75: =B75+C75 -> 4171 | E75: =D75*B$77/D$77 -> 1106.8577 | F75: =D75*C$77/D$77 -> 3064.1423
A76: =Analysis!A60 -> No | B76: =Analysis!C60 -> 469 | C76: =Analysis!B60-Analysis!C60 -> 2403 | D76: =B76+C76 -> 2872 | E76: =D76*B$77/D$77 -> 762.14227 | F76: =D76*C$77/D$77 -> 2109.8577
A77: Total | B77: =SUM(B75:B76) -> 1869 | C77: =SUM(C75:C76) -> 5174 | D77: =SUM(D75:D76) -> 7043

Sheet Risk_Segments
A1: Highest-risk customer profiles (contract x internet x payment)
A2: Ranked by churn rate among combinations with at least 100 customers (smaller groups are too noisy to rank).
A4: Contract | B4: Internet service | C4: Payment method | D4: Customers | E4: Churn rate | F4: Lost MRR | G4: Rate if ranked | H4: Rank | I4: Minimum customers to rank | J4: 100
A5: Month-to-month | B5: Fiber optic | C5: Electronic check | D5: =COUNTIFS(Data!$P$2:$P$7044,A5,Data!$I$2:$I$7044,B5,Data!$R$2:$R$7044,C5) -> 1307 | E5: =IFERROR(COUNTIFS(Data!$P$2:$P$7044,A5,Data!$I$2:$I$7044,B5,Data!$R$2:$R$7044,C5,Data!$W$2:$W$7044,1)/D5,0) -> 0.60367253 | F5: =SUMIFS(Data!$AA$2:$AA$7044,Data!$P$2:$P$7044,A5,Data!$I$2:$I$7044,B5,Data!$R$2:$R$7044,C5) -> 68281.5 | G5: =IF(D5>=$J$4,E5,"") -> 0.60367253 | H5: =IF(G5="","",RANK(G5,$G$5:$G$40)) -> 1
A6: Month-to-month | B6: Fiber optic | C6: Mailed check | D6: =COUNTIFS(Data!$P$2:$P$7044,A6,Data!$I$2:$I$7044,B6,Data!$R$2:$R$7044,C6) -> 201 | E6: =IFERROR(COUNTIFS(Data!$P$2:$P$7044,A6,Data!$I$2:$I$7044,B6,Data!$R$2:$R$7044,C6,Data!$W$2:$W$7044,1)/D6,0) -> 0.50746269 | F6: =SUMIFS(Data!$AA$2:$AA$7044,Data!$P$2:$P$7044,A6,Data!$I$2:$I$7044,B6,Data!$R$2:$R$7044,C6) -> 8407.25 | G6: =IF(D6>=$J$4,E6,"") -> 0.50746269 | H6: =IF(G6="","",RANK(G6,$G$5:$G$40)) -> 2
A7: Month-to-month | B7: Fiber optic | C7: Bank transfer (automatic) | D7: =COUNTIFS(Data!$P$2:$P$7044,A7,Data!$I$2:$I$7044,B7,Data!$R$2:$R$7044,C7) -> 327 | E7: =IFERROR(COUNTIFS(Data!$P$2:$P$7044,A7,Data!$I$2:$I$7044,B7,Data!$R$2:$R$7044,C7,Data!$W$2:$W$7044,1)/D7,0) -> 0.45565749 | F7: =SUMIFS(Data!$AA$2:$AA$7044,Data!$P$2:$P$7044,A7,Data!$I$2:$I$7044,B7,Data!$R$2:$R$7044,C7) -> 13062.1 | G7: =IF(D7>=$J$4,E7,"") -> 0.45565749 | H7: =IF(G7="","",RANK(G7,$G$5:$G$40)) -> 3
A8: Month-to-month | B8: Fiber optic | C8: Credit card (automatic) | D8: =COUNTIFS(Data!$P$2:$P$7044,A8,Data!$I$2:$I$7044,B8,Data!$R$2:$R$7044,C8) -> 293 | E8: =IFERROR(COUNTIFS(Data!$P$2:$P$7044,A8,Data!$I$2:$I$7044,B8,Data!$R$2:$R$7044,C8,Data!$W$2:$W$7044,1)/D8,0) -> 0.41638225 | F8: =SUMIFS(Data!$AA$2:$AA$7044,Data!$P$2:$P$7044,A8,Data!$I$2:$I$7044,B8,Data!$R$2:$R$7044,C8) -> 10731.15 | G8: =IF(D8>=$J$4,E8,"") -> 0.41638225 | H8: =IF(G8="","",RANK(G8,$G$5:$G$40)) -> 4
A9: Month-to-month | B9: DSL | C9: Electronic check | D9: =COUNTIFS(Data!$P$2:$P$7044,A9,Data!$I$2:$I$7044,B9,Data!$R$2:$R$7044,C9) -> 474 | E9: =IFERROR(COUNTIFS(Data!$P$2:$P$7044,A9,Data!$I$2:$I$7044,B9,Data!$R$2:$R$7044,C9,Data!$W$2:$W$7044,1)/D9,0) -> 0.40506329 | F9: =SUMIFS(Data!$AA$2:$AA$7044,Data!$P$2:$P$7044,A9,Data!$I$2:$I$7044,B9,Data!$R$2:$R$7044,C9) -> 8776.45 | G9: =IF(D9>=$J$4,E9,"") -> 0.40506329 | H9: =IF(G9="","",RANK(G9,$G$5:$G$40)) -> 5
A10: Month-to-month | B10: DSL | C10: Mailed check | D10: =COUNTIFS(Data!$P$2:$P$7044,A10,Data!$I$2:$I$7044,B10,Data!$R$2:$R$7044,C10) -> 367 | E10: =IFERROR(COUNTIFS(Data!$P$2:$P$7044,A10,Data!$I$2:$I$7044,B10,Data!$R$2:$R$7044,C10,Data!$W$2:$W$7044,1)/D10,0) -> 0.30790191 | F10: =SUMIFS(Data!$AA$2:$AA$7044,Data!$P$2:$P$7044,A10,Data!$I$2:$I$7044,B10,Data!$R$2:$R$7044,C10) -> 5292.1 | G10: =IF(D10>=$J$4,E10,"") -> 0.30790191 | H10: =IF(G10="","",RANK(G10,$G$5:$G$40)) -> 6
A11: Month-to-month | B11: DSL | C11: Credit card (automatic) | D11: =COUNTIFS(Data!$P$2:$P$7044,A11,Data!$I$2:$I$7044,B11,Data!$R$2:$R$7044,C11) -> 185 | E11: =IFERROR(COUNTIFS(Data!$P$2:$P$7044,A11,Data!$I$2:$I$7044,B11,Data!$R$2:$R$7044,C11,Data!$W$2:$W$7044,1)/D11,0) -> 0.27027027 | F11: =SUMIFS(Data!$AA$2:$AA$7044,Data!$P$2:$P$7044,A11,Data!$I$2:$I$7044,B11,Data!$R$2:$R$7044,C11) -> 2474.8 | G11: =IF(D11>=$J$4,E11,"") -> 0.27027027 | H11: =IF(G11="","",RANK(G11,$G$5:$G$40)) -> 7
A12: One year | B12: Fiber optic | C12: Electronic check | D12: =COUNTIFS(Data!$P$2:$P$7044,A12,Data!$I$2:$I$7044,B12,Data!$R$2:$R$7044,C12) -> 196 | E12: =IFERROR(COUNTIFS(Data!$P$2:$P$7044,A12,Data!$I$2:$I$7044,B12,Data!$R$2:$R$7044,C12,Data!$W$2:$W$7044,1)/D12,0) -> 0.26020408 | F12: =SUMIFS(Data!$AA$2:$AA$7044,Data!$P$2:$P$7044,A12,Data!$I$2:$I$7044,B12,Data!$R$2:$R$7044,C12) -> 5149.65 | G12: =IF(D12>=$J$4,E12,"") -> 0.26020408 | H12: =IF(G12="","",RANK(G12,$G$5:$G$40)) -> 8
A13: Month-to-month | B13: No | C13: Mailed check | D13: =COUNTIFS(Data!$P$2:$P$7044,A13,Data!$I$2:$I$7044,B13,Data!$R$2:$R$7044,C13) -> 325 | E13: =IFERROR(COUNTIFS(Data!$P$2:$P$7044,A13,Data!$I$2:$I$7044,B13,Data!$R$2:$R$7044,C13,Data!$W$2:$W$7044,1)/D13,0) -> 0.20615385 | F13: =SUMIFS(Data!$AA$2:$AA$7044,Data!$P$2:$P$7044,A13,Data!$I$2:$I$7044,B13,Data!$R$2:$R$7044,C13) -> 1345.05 | G13: =IF(D13>=$J$4,E13,"") -> 0.20615385 | H13: =IF(G13="","",RANK(G13,$G$5:$G$40)) -> 9
A14: Month-to-month | B14: DSL | C14: Bank transfer (automatic) | D14: =COUNTIFS(Data!$P$2:$P$7044,A14,Data!$I$2:$I$7044,B14,Data!$R$2:$R$7044,C14) -> 197 | E14: =IFERROR(COUNTIFS(Data!$P$2:$P$7044,A14,Data!$I$2:$I$7044,B14,Data!$R$2:$R$7044,C14,Data!$W$2:$W$7044,1)/D14,0) -> 0.19796954 | F14: =SUMIFS(Data!$AA$2:$AA$7044,Data!$P$2:$P$7044,A14,Data!$I$2:$I$7044,B14,Data!$R$2:$R$7044,C14) -> 1823.9 | G14: =IF(D14>=$J$4,E14,"") -> 0.19796954 | H14: =IF(G14="","",RANK(G14,$G$5:$G$40)) -> 10
A15: One year | B15: Fiber optic | C15: Credit card (automatic) | D15: =COUNTIFS(Data!$P$2:$P$7044,A15,Data!$I$2:$I$7044,B15,Data!$R$2:$R$7044,C15) -> 150 | E15: =IFERROR(COUNTIFS(Data!$P$2:$P$7044,A15,Data!$I$2:$I$7044,B15,Data!$R$2:$R$7044,C15,Data!$W$2:$W$7044,1)/D15,0) -> 0.15333333 | F15: =SUMIFS(Data!$AA$2:$AA$7044,Data!$P$2:$P$7044,A15,Data!$I$2:$I$7044,B15,Data!$R$2:$R$7044,C15) -> 2392.35 | G15: =IF(D15>=$J$4,E15,"") -> 0.15333333 | H15: =IF(G15="","",RANK(G15,$G$5:$G$40)) -> 11
A16: One year | B16: Fiber optic | C16: Bank transfer (automatic) | D16: =COUNTIFS(Data!$P$2:$P$7044,A16,Data!$I$2:$I$7044,B16,Data!$R$2:$R$7044,C16) -> 157 | E16: =IFERROR(COUNTIFS(Data!$P$2:$P$7044,A16,Data!$I$2:$I$7044,B16,Data!$R$2:$R$7044,C16,Data!$W$2:$W$7044,1)/D16,0) -> 0.14649682 | F16: =SUMIFS(Data!$AA$2:$AA$7044,Data!$P$2:$P$7044,A16,Data!$I$2:$I$7044,B16,Data!$R$2:$R$7044,C16) -> 2344.35 | G16: =IF(D16>=$J$4,E16,"") -> 0.14649682 | H16: =IF(G16="","",RANK(G16,$G$5:$G$40)) -> 12
... A40: Two year | B40: No | C40: Electronic check | D40: =COUNTIFS(Data!$P$2:$P$7044,A40,Data!$I$2:$I$7044,B40,Data!$R$2:$R$7044,C40) -> 18 | E40: =IFERROR(COUNTIFS(Data!$P$2:$P$7044,A40,Data!$I$2:$I$7044,B40,Data!$R$2:$R$7044,C40,Data!$W$2:$W$7044,1)/D40,0) -> 0 | F40: =SUMIFS(Data!$AA$2:$AA$7044,Data!$P$2:$P$7044,A40,Data!$I$2:$I$7044,B40,Data!$R$2:$R$7044,C40) -> 0 | G40: =IF(D40>=$J$4,E40,"") | H40: =IF(G40="","",RANK(G40,$G$5:$G$40))

Sheet At_Risk
A1: Who to save: the risk score and the active customers it flags
A2: Risk score = 1 point each for month-to-month, fiber optic, electronic check, tenure <= 12 months, no tech support, no online security. The churn rate column checks that a higher score really means more churn.
A4: Risk score | B4: All customers | C4: Churned | D4: Churn rate | E4: Active customers | F4: Active customers' MRR | G4: Risk level
A5: 0 | B5: =COUNTIFS(Data!$AB$2:$AB$7044,A5) -> 1354 | C5: =COUNTIFS(Data!$AB$2:$AB$7044,A5,Data!$W$2:$W$7044,1) -> 26 | D5: =IFERROR(C5/B5,0) -> 0.019202363 | E5: =COUNTIFS(Data!$AB$2:$AB$7044,A5,Data!$W$2:$W$7044,0) -> 1328 | F5: =SUMIFS(Data!$S$2:$S$7044,Data!$AB$2:$AB$7044,A5,Data!$W$2:$W$7044,0) -> 53234.4 | G5: =IF(A5>=5,"High",IF(A5>=3,"Medium","Low")) -> Low
A6: 1 | B6: =COUNTIFS(Data!$AB$2:$AB$7044,A6) -> 987 | C6: =COUNTIFS(Data!$AB$2:$AB$7044,A6,Data!$W$2:$W$7044,1) -> 62 | D6: =IFERROR(C6/B6,0) -> 0.062816616 | E6: =COUNTIFS(Data!$AB$2:$AB$7044,A6,Data!$W$2:$W$7044,0) -> 925 | F6: =SUMIFS(Data!$S$2:$S$7044,Data!$AB$2:$AB$7044,A6,Data!$W$2:$W$7044,0) -> 57912.5 | G6: =IF(A6>=5,"High",IF(A6>=3,"Medium","Low")) -> Low
A7: 2 | B7: =COUNTIFS(Data!$AB$2:$AB$7044,A7) -> 1196 | C7: =COUNTIFS(Data!$AB$2:$AB$7044,A7,Data!$W$2:$W$7044,1) -> 180 | D7: =IFERROR(C7/B7,0) -> 0.15050167 | E7: =COUNTIFS(Data!$AB$2:$AB$7044,A7,Data!$W$2:$W$7044,0) -> 1016 | F7: =SUMIFS(Data!$S$2:$S$7044,Data!$AB$2:$AB$7044,A7,Data!$W$2:$W$7044,0) -> 62718.95 | G7: =IF(A7>=5,"High",IF(A7>=3,"Medium","Low")) -> Low
A8: 3 | B8: =COUNTIFS(Data!$AB$2:$AB$7044,A8) -> 939 | C8: =COUNTIFS(Data!$AB$2:$AB$7044,A8,Data!$W$2:$W$7044,1) -> 216 | D8: =IFERROR(C8/B8,0) -> 0.23003195 | E8: =COUNTIFS(Data!$AB$2:$AB$7044,A8,Data!$W$2:$W$7044,0) -> 723 | F8: =SUMIFS(Data!$S$2:$S$7044,Data!$AB$2:$AB$7044,A8,Data!$W$2:$W$7044,0) -> 53233.35 | G8: =IF(A8>=5,"High",IF(A8>=3,"Medium","Low")) -> Medium
A9: 4 | B9: =COUNTIFS(Data!$AB$2:$AB$7044,A9) -> 1082 | C9: =COUNTIFS(Data!$AB$2:$AB$7044,A9,Data!$W$2:$W$7044,1) -> 433 | D9: =IFERROR(C9/B9,0) -> 0.40018484 | E9: =COUNTIFS(Data!$AB$2:$AB$7044,A9,Data!$W$2:$W$7044,0) -> 649 | F9: =SUMIFS(Data!$S$2:$S$7044,Data!$AB$2:$AB$7044,A9,Data!$W$2:$W$7044,0) -> 48046.85 | G9: =IF(A9>=5,"High",IF(A9>=3,"Medium","Low")) -> Medium
A10: 5 | B10: =COUNTIFS(Data!$AB$2:$AB$7044,A10) -> 941 | C10: =COUNTIFS(Data!$AB$2:$AB$7044,A10,Data!$W$2:$W$7044,1) -> 547 | D10: =IFERROR(C10/B10,0) -> 0.58129649 | E10: =COUNTIFS(Data!$AB$2:$AB$7044,A10,Data!$W$2:$W$7044,0) -> 394 | F10: =SUMIFS(Data!$S$2:$S$7044,Data!$AB$2:$AB$7044,A10,Data!$W$2:$W$7044,0) -> 30771.55 | G10: =IF(A10>=5,"High",IF(A10>=3,"Medium","Low")) -> High
A11: 6 | B11: =COUNTIFS(Data!$AB$2:$AB$7044,A11) -> 544 | C11: =COUNTIFS(Data!$AB$2:$AB$7044,A11,Data!$W$2:$W$7044,1) -> 405 | D11: =IFERROR(C11/B11,0) -> 0.74448529 | E11: =COUNTIFS(Data!$AB$2:$AB$7044,A11,Data!$W$2:$W$7044,0) -> 139 | F11: =SUMIFS(Data!$S$2:$S$7044,Data!$AB$2:$AB$7044,A11,Data!$W$2:$W$7044,0) -> 11068.15 | G11: =IF(A11>=5,"High",IF(A11>=3,"Medium","Low")) -> High
A14: Active high-risk customers (score 5-6): the retention target
A15: Customers | B15: =COUNTIFS(Data!$AC$2:$AC$7044,"High",Data!$W$2:$W$7044,0) -> 533
A16: Monthly revenue at stake | B16: =SUMIFS(Data!$S$2:$S$7044,Data!$AC$2:$AC$7044,"High",Data!$W$2:$W$7044,0) -> 41839.7
A17: Average monthly bill | B17: =IFERROR(B16/B15,0) -> 78.498499
A18: Historical churn rate of high-risk customers | B18: =IFERROR(COUNTIFS(Data!$AC$2:$AC$7044,"High",Data!$W$2:$W$7044,1)/COUNTIFS(Data!$AC$2:$AC$7044,"High"),0) -> 0.64107744
A19: Expected monthly revenue lost if nothing is done | B19: =B16*B18 -> 26822.488
A20: Annualized | B20: =B19*12 -> 321869.85
A24: To see the individual customers: go to the Data sheet, filter Risk_Level = High and Churn = No.

Sheet Retention_Scenario
A1: What-if: offer at-risk customers a discount to move to a 1-year contract
A2: Blue cells on yellow are inputs: change them to test scenarios. Black cells are formulas; green cells link to other sheets.
A4: Inputs and assumptions
A5: Target customers (active, high risk) | B5: =At_Risk!B15 -> 533 | C5: Linked from At_Risk.
A6: Average monthly bill | B6: =At_Risk!B17 -> 78.498499 | C6: Linked from At_Risk.
A7: Churn rate if nothing is done | B7: =At_Risk!B18 -> 0.64107744 | C7: Historical churn rate of high-risk customers.
A8: Churn rate after moving to a 1-year contract | B8: =Analysis!D10 -> 0.11269518 | C8: Assumption: switchers behave like current 1-year customers. Likely optimistic, since switchers start out higher-risk.
A9: Offer acceptance rate | B9: 0.25 | C9: Assumption: 25% of targeted customers accept. Test it with a pilot (see Test_Design).
A10: Discount offered | B10: 0.15 | C10: Assumption: 15% off the monthly bill for 12 months.
A11: Months in the period | B11: 12 | C11: One contract year.
A13: Results
A14: Customers who accept | B14: =B5*B9 -> 133.25
A15: Churners avoided | B15: =B14*(B7-B8) -> 70.406936
A16: Revenue kept from avoided churners (after discount) | B16: =B15*B6*(1-B10)*B11 -> 56373.756
A17: Discount given to customers who would have stayed anyway | B17: =(B14-B15)*B6*B10*B11 -> 8879.5551
A18: Net revenue gained over the period | B18: =B16-B17 -> 47494.201
A19: Return per $1 of discount | B19: =IFERROR(B18/(B17+B15*B6*B10*B11),0) -> 2.5225484
A22: Sensitivity: net revenue gained by acceptance rate (rows) and discount (columns)
A23: Acceptance \ Discount | B23: 0.05 | C23: 0.1 | D23: 0.15 | E23: 0.2 | F23: 0.25
A24: 0.1 | B24: =($B$5*$A24*($B$7-$B$8))*$B$6*(1-B$23)*$B$11-($B$5*$A24-$B$5*$A24*($B$7-$B$8))*$B$6*B$23*$B$11 -> 24018.444 | C24: =($B$5*$A24*($B$7-$B$8))*$B$6*(1-C$23)*$B$11-($B$5*$A24-$B$5*$A24*($B$7-$B$8))*$B$6*C$23*$B$11 -> 21508.062 | D24: =($B$5*$A24*($B$7-$B$8))*$B$6*(1-D$23)*$B$11-($B$5*$A24-$B$5*$A24*($B$7-$B$8))*$B$6*D$23*$B$11 -> 18997.68 | E24: =($B$5*$A24*($B$7-$B$8))*$B$6*(1-E$23)*$B$11-($B$5*$A24-$B$5*$A24*($B$7-$B$8))*$B$6*E$23*$B$11 -> 16487.298 | F24: =($B$5*$A24*($B$7-$B$8))*$B$6*(1-F$23)*$B$11-($B$5*$A24-$B$5*$A24*($B$7-$B$8))*$B$6*F$23*$B$11 -> 13976.916
A25: 0.15 | B25: =($B$5*$A25*($B$7-$B$8))*$B$6*(1-B$23)*$B$11-($B$5*$A25-$B$5*$A25*($B$7-$B$8))*$B$6*B$23*$B$11 -> 36027.667 | C25: =($B$5*$A25*($B$7-$B$8))*$B$6*(1-C$23)*$B$11-($B$5*$A25-$B$5*$A25*($B$7-$B$8))*$B$6*C$23*$B$11 -> 32262.094 | D25: =($B$5*$A25*($B$7-$B$8))*$B$6*(1-D$23)*$B$11-($B$5*$A25-$B$5*$A25*($B$7-$B$8))*$B$6*D$23*$B$11 -> 28496.521 | E25: =($B$5*$A25*($B$7-$B$8))*$B$6*(1-E$23)*$B$11-($B$5*$A25-$B$5*$A25*($B$7-$B$8))*$B$6*E$23*$B$11 -> 24730.948 | F25: =($B$5*$A25*($B$7-$B$8))*$B$6*(1-F$23)*$B$11-($B$5*$A25-$B$5*$A25*($B$7-$B$8))*$B$6*F$23*$B$11 -> 20965.375
A26: 0.2 | B26: =($B$5*$A26*($B$7-$B$8))*$B$6*(1-B$23)*$B$11-($B$5*$A26-$B$5*$A26*($B$7-$B$8))*$B$6*B$23*$B$11 -> 48036.889 | C26: =($B$5*$A26*($B$7-$B$8))*$B$6*(1-C$23)*$B$11-($B$5*$A26-$B$5*$A26*($B$7-$B$8))*$B$6*C$23*$B$11 -> 43016.125 | D26: =($B$5*$A26*($B$7-$B$8))*$B$6*(1-D$23)*$B$11-($B$5*$A26-$B$5*$A26*($B$7-$B$8))*$B$6*D$23*$B$11 -> 37995.361 | E26: =($B$5*$A26*($B$7-$B$8))*$B$6*(1-E$23)*$B$11-($B$5*$A26-$B$5*$A26*($B$7-$B$8))*$B$6*E$23*$B$11 -> 32974.597 | F26: =($B$5*$A26*($B$7-$B$8))*$B$6*(1-F$23)*$B$11-($B$5*$A26-$B$5*$A26*($B$7-$B$8))*$B$6*F$23*$B$11 -> 27953.833
A27: 0.25 | B27: =($B$5*$A27*($B$7-$B$8))*$B$6*(1-B$23)*$B$11-($B$5*$A27-$B$5*$A27*($B$7-$B$8))*$B$6*B$23*$B$11 -> 60046.111 | C27: =($B$5*$A27*($B$7-$B$8))*$B$6*(1-C$23)*$B$11-($B$5*$A27-$B$5*$A27*($B$7-$B$8))*$B$6*C$23*$B$11 -> 53770.156 | D27: =($B$5*$A27*($B$7-$B$8))*$B$6*(1-D$23)*$B$11-($B$5*$A27-$B$5*$A27*($B$7-$B$8))*$B$6*D$23*$B$11 -> 47494.201 | E27: =($B$5*$A27*($B$7-$B$8))*$B$6*(1-E$23)*$B$11-($B$5*$A27-$B$5*$A27*($B$7-$B$8))*$B$6*E$23*$B$11 -> 41218.246 | F27: =($B$5*$A27*($B$7-$B$8))*$B$6*(1-F$23)*$B$11-($B$5*$A27-$B$5*$A27*($B$7-$B$8))*$B$6*F$23*$B$11 -> 34942.291
A28: 0.3 | B28: =($B$5*$A28*($B$7-$B$8))*$B$6*(1-B$23)*$B$11-($B$5*$A28-$B$5*$A28*($B$7-$B$8))*$B$6*B$23*$B$11 -> 72055.333 | C28: =($B$5*$A28*($B$7-$B$8))*$B$6*(1-C$23)*$B$11-($B$5*$A28-$B$5*$A28*($B$7-$B$8))*$B$6*C$23*$B$11 -> 64524.187 | D28: =($B$5*$A28*($B$7-$B$8))*$B$6*(1-D$23)*$B$11-($B$5*$A28-$B$5*$A28*($B$7-$B$8))*$B$6*D$23*$B$11 -> 56993.041 | E28: =($B$5*$A28*($B$7-$B$8))*$B$6*(1-E$23)*$B$11-($B$5*$A28-$B$5*$A28*($B$7-$B$8))*$B$6*E$23*$B$11 -> 49461.895 | F28: =($B$5*$A28*($B$7-$B$8))*$B$6*(1-F$23)*$B$11-($B$5*$A28-$B$5*$A28*($B$7-$B$8))*$B$6*F$23*$B$11 -> 41930.749
A29: 0.4 | B29: =($B$5*$A29*($B$7-$B$8))*$B$6*(1-B$23)*$B$11-($B$5*$A29-$B$5*$A29*($B$7-$B$8))*$B$6*B$23*$B$11 -> 96073.777 | C29: =($B$5*$A29*($B$7-$B$8))*$B$6*(1-C$23)*$B$11-($B$5*$A29-$B$5*$A29*($B$7-$B$8))*$B$6*C$23*$B$11 -> 86032.249 | D29: =($B$5*$A29*($B$7-$B$8))*$B$6*(1-D$23)*$B$11-($B$5*$A29-$B$5*$A29*($B$7-$B$8))*$B$6*D$23*$B$11 -> 75990.721 | E29: =($B$5*$A29*($B$7-$B$8))*$B$6*(1-E$23)*$B$11-($B$5*$A29-$B$5*$A29*($B$7-$B$8))*$B$6*E$23*$B$11 -> 65949.193 | F29: =($B$5*$A29*($B$7-$B$8))*$B$6*(1-F$23)*$B$11-($B$5*$A29-$B$5*$A29*($B$7-$B$8))*$B$6*F$23*$B$11 -> 55907.665
A31: Reading it: the offer pays off at every combination shown because high-risk customers churn far more than 1-year customers. The biggest uncertainty is whether switchers really behave like existing 1-year customers; a pilot test answers that.

Sheet Test_Design
A1: Pilot test design: how many customers do we need?
A2: Before rolling out the offer, test it: randomly give it to half of the target group and compare churn. This sheet sizes the test.
A5: Baseline churn rate (control group) | B5: =At_Risk!B18 -> 0.64107744 | C5: High-risk customers' historical churn.
A6: Smallest reduction worth detecting (percentage points) | B6: 0.1 | C6: Assumption: we only care if the offer cuts churn by 10 points or more.
A7: Expected churn rate with the offer | B7: =B5-B6 -> 0.54107744
A8: Significance level (alpha) | B8: 0.05 | C8: Standard 5%: accept a 5% chance of a false positive.
A9: Power | B9: 0.8 | C9: Standard 80%: an 80% chance of detecting a real effect.
A10: Customers needed per group | B10: =ROUNDUP(((NORMSINV(1-B8/2)*SQRT(2*((B5+B7)/2)*(1-(B5+B7)/2))+NORMSINV(B9)*SQRT(B5*(1-B5)+B7*(1-B7)))^2)/(B5-B7)^2,0) -> 379 | C10: Standard two-proportion sample-size formula.
A11: Total customers needed (2 groups) | B11: =B10*2 -> 758
A12: Active high-risk customers available | B12: =At_Risk!B15 -> 533
A13: Enough customers for the test? | B13: =IF(B12>=B11,"Yes","No: widen the target to medium risk or run longer") -> No: widen the target to medium risk or run longer
A15: Primary metric: churn rate after 3 months. Guardrail: average revenue per customer (the discount must not cost more than it saves).
